{"Beverly Hills - 054 - 1776": 0, "Lake Park #1 - 158 - 1567": 0, "Jet Port #1 - 153 - 867": 0, "Choppee - 108 - 622": 0, "Sampit - 131 - 609": 0, "Murrell's Inlet No. 2 - 118 - 630": 0, "Red Hill #2 - 193 - 887": 0, "Ocean Forest #2 - 182 - 822": 0, "Mt. Pleasant 7 - 307 - 287": 0, "Salem - 194 - 830": 0, "Nichols - 017 - 1035": 0, "Howe Hall 2 - 056 - 1749": 0, "Prospect - 051 - 1525": 0, "Mt. Pleasant 2 - 302 - 284": 0, "Foster Creek 3 - 078 - 1705": 0, "Christ Church - 008 - 229": 0, "Emerald Forest #3 - 132 - 889": 0, "Enterprise - 133 - 845": 0, "Georgetown No. 3 - 112 - 611": 0, "Georgetown No. 4 - 113 - 612": 0, "Bushy Park - 088 - 1758": 0, "Adrian - 101 - 778": 0, "Windy Hill #1 - 217 - 872": 0, "Pimlico - 035 - 1789": 0, "Charleston 9 - 209 - 279": 0, "Pine Grove - 098 - 1790": 0, "Racepath #2 - 190 - 828": 0, "Penny Royal - 127 - 604": 0, "Mt. Pleasant 31 - 331 - 362": 0, "Coastal Lane #2 - 117 - 855": 0, "Kingstree No.3 - 016 - 1362": 0, "Myersville - 121 - 632": 0, "Vox - 062 - 1518": 0, "Pawleys Swamp - 185 - 824": 0, "Cherry Grove #2 - 114 - 849": 0, "Folly Grove - 110 - 635": 0, "Mcclellanville - 100 - 230": 0, "Poplar Hill - 187 - 825": 0, "Dogwood - 123 - 853": 0, "Ocean Forest #1 - 181 - 821": 0, "Discovery - 066 - 1733": 0, "Glenns Bay - 142 - 846": 0, "Murrell's Inlet No. 3 - 119 - 628": 0, "Cypress - 085 - 1757": 0, "Taylorsville - 209 - 840": 0, "Surfside #1 - 204 - 835": 0, "Pawley's Island No. 4 - 125 - 625": 0, "Marlowe #3 - 222 - 880": 0, "Burgess #2 - 109 - 884": 0, "Garden City #4 - 141 - 864": 0, "Charleston 10 - 210 - 274": 0, "Dogbluff - 122 - 791": 0, "Bethera - 002 - 1697": 0, "Medway - 058 - 1784": 0, "Potato Bed Ferry - 130 - 618": 0, "S West Mullins - 014 - 1032": 0, "Henry-Poplar Hill - 012 - 1366": 0, "Red Hill #1 - 192 - 859": 0, "Nexton - 097 - 1753": 0, "Spring Gully - 133 - 608": 0, "Mt. Pleasant 12 - 312 - 346": 0, "Boulder Bluff - 087 - 1785": 0, "Homewood - 147 - 799": 0, "Mt. Pleasant 38 - 338 - 366": 0, "Stratford 5 - 074 - 1734": 0, "Cainhoy - 007 - 1748": 0, "Royle - 071 - 1729": 0, "Mt. Pleasant 3 - 303 - 285": 0, "Brooksville #2 - 223 - 783": 0, "Isle Of Palms 1B - 011 - 336": 0, "Fork - 020 - 1799": 0, "Jordanville - 155 - 804": 0, "Santee - 132 - 619": 0, "Kingstree No.2 - 015 - 1361": 0, "Joyner Swamp - 156 - 805": 0, "Harbour Lake - 079 - 1761": 0, "North Conway #2 - 177 - 818": 0, "Mt. Calvary - 009 - 1804": 0, "Dream Keepers - 109 - 607": 0, "Juniper Bay - 157 - 806": 0, "Deerfield - 121 - 848": 0, "Muddy Creek - 035 - 1365": 0, "Charleston 2 - 202 - 277": 0, "Lake City No. 4 - 041 - 1537": 0, "Sweet Home - 208 - 839": 0, "Socastee #1 - 199 - 866": 0, "Little River #2 - 161 - 861": 0, "Wampee - 212 - 891": 0, "Hemingway - 011 - 1364": 0, "Devon Forest 2 - 015 - 1738": 0, "Awendaw - 004 - 228": 0, "Pleasant Hill - 008 - 1810": 0, "Port Harrelson - 188 - 826": 0, "Daniel Island 1 - 012 - 1745": 0, "Johnsonville - 036 - 1529": 0, "Carolina Bays - 224 - 871": 0, "Kingstree No.4 - 017 - 1363": 0, "Mt. Pleasant 21 - 321 - 355": 0, "Pawley's Island No. 2 - 123 - 626": 0, "Whitesville 2 - 060 - 1782": 0, "Myrtlewood #1 - 171 - 814": 0, "River Oaks - 226 - 878": 0, "Brown's Ferry - 105 - 615": 0, "Mt. Pleasant 9 - 309 - 351": 0, "The Village - 063 - 1747": 0, "Cordesville - 010 - 1701": 0, "Mt. Pleasant 17 - 317 - 292": 0, "Lake City No. 1 - 038 - 1540": 0, "Piney Forest - 027 - 1371": 0, "Devon Forest 1 - 014 - 1737": 0, "Mt. Pleasant 23 - 323 - 226": 0, "Myrtlewood #2 - 172 - 815": 0, "Hickory Grove - 145 - 2256": 0, "Little River #1 - 160 - 808": 0, "Mt. Pleasant 35 - 335 - 368": 0, "Isle Of Palms 1C - 012 - 335": 0, "Shulerville - 041 - 1723": 0, "Mt. Pleasant 8 - 308 - 288": 0, "Burgess #1 - 108 - 883": 0, "Stratford 3 - 046 - 1732": 0, "Cresent - 119 - 789": 0, "Maple - 164 - 810": 0, "West Loris - 214 - 843": 0, "Mt. Pleasant 27 - 327 - 358": 0, "Horry - 148 - 800": 0, "Mt. Pleasant 24 - 324 - 356": 0, "Wild Wing - 216 - 863": 0, "Myrtlewood #3 - 173 - 856": 0, "Mcbeth - 030 - 1716": 0, "Methodist-Mill Swamp - 166 - 811": 0, "Sea Oats #1 - 195 - 831": 0, "Charleston 6 - 206 - 278": 0, "Mt. Pleasant 5 - 305 - 369": 0, "Emerald Forest #2 - 131 - 879": 0, "Pawley's Island No. 1 - 122 - 627": 0, "Manning - 018 - 1801": 0, "Mt. Pleasant 13 - 313 - 347": 0, "Pawley's Island No. 5 - 126 - 624": 0, "Winyah Bay - 134 - 603": 0, "Mt. Pleasant 33 - 333 - 227": 0, "Charleston 8 - 208 - 281": 0, "Ocean Forest #3 - 183 - 823": 0, "Pleasant Hill - 129 - 623": 0, "Sangaree 1 - 038 - 1731": 0, "Nixons Xroads #3 - 225 - 816": 0, "Mt. Pleasant 39 - 339 - 367": 0, "Central - 005 - 1376": 0, "Cool Springs - 118 - 788": 0, "Mt. Pleasant 34 - 334 - 361": 0, "Kingsburg-Stone - 037 - 1526": 0, "Live Oak - 163 - 809": 0, "Horseshoe - 094 - 1766": 0, "Allsbrook - 102 - 779": 0, "West Conway - 213 - 842": 0, "Spring Branch - 203 - 834": 0, "Bayboro-Gurley - 105 - 782": 0, "East Loris - 128 - 792": 0, "Surfside #4 - 207 - 838": 0, "Stone Lake - 073 - 1742": 0, "St. James - 080 - 1707": 0, "Mt. Pleasant 32 - 332 - 363": 0, "Britton's Neck - 001 - 1021": 0, "Sedgefield 3 - 100 - 1792": 0, "N West Mullins - 013 - 1031": 0, "Socastee #3 - 201 - 2258": 0, "Weatherstone - 084 - 1752": 0, "Sea Oats #2 - 196 - 832": 0, "S East Mullins - 016 - 1034": 0, "Ocean Drive #2 - 180 - 820": 0, "Mt. Pleasant 28 - 328 - 225": 0, "Friendship - 002 - 1022": 0, "Liberty Hall - 057 - 1791": 0, "Fifty-Two - 093 - 1770": 0, "Murrell's Inlet No. 4 - 120 - 629": 0, "Ebenezer - 129 - 793": 0, "Daisy - 120 - 790": 0, "Lake City No. 2 - 039 - 1541": 0, "Pomflant - 099 - 1750": 0, "Garden City #1 - 138 - 796": 0, "Mt. Pleasant 19 - 319 - 291": 0, "Little River #3 - 162 - 862": 0, "Lake Park #3 - 229 - 1566": 0, "Shell - 198 - 833": 0, "Mt. Pleasant 6 - 306 - 289": 0, "Coastal Carolina - 115 - 860": 0, "Surfside #3 - 206 - 837": 0, "Charleston 4 - 204 - 270": 0, "Forestbrook - 135 - 2257": 0, "Garden City #3 - 140 - 865": 0, "Jackson Bluff - 150 - 854": 0, "Marlowe #2 - 220 - 882": 0, "Plantersville - 128 - 621": 0, "Carolina Forest #2 - 111 - 877": 0, "Rains - 004 - 1023": 0, "Burgess #4 - 221 - 886": 0, "Hanahan 5 - 068 - 1788": 0, "North Conway #1 - 176 - 817": 0, "Marlowe #1 - 165 - 881": 0, "Toddville - 211 - 841": 0, "Carolina Forest #1 - 110 - 876": 0, "Palmetto Bays - 184 - 870": 0, "Mt. Olive - 168 - 812": 0, "Windy Hill #2 - 218 - 874": 0, "Carnes Cross Roads 1 - 008 - 1783": 0, "Howe Hall 1 - 055 - 1711": 0, "Black River - 104 - 614": 0, "Mt. Pleasant 15 - 315 - 290": 0, "Georgetown No. 1 - 111 - 606": 0, "Mill Branch - 046 - 1528": 0, "Cedar Grove - 112 - 785": 0, "Dunes #3 - 126 - 852": 0, "Isle Of Palms 1A - 010 - 268": 0, "Ocean Drive #1 - 179 - 819": 0, "Sangaree 3 - 040 - 1730": 0, "Pee Dee - 115 - 634": 0, "Jerigans Crossroads - 152 - 803": 0, "Pamplico No. 2 - 050 - 1527": 0, "Aynor - 104 - 781": 0, "Inland - 149 - 801": 0, "Atlantic Beach - 103 - 780": 0, "Mt. Vernon - 169 - 813": 0, "Georgetown No. 5 - 114 - 605": 0, "Red Bluff - 191 - 829": 0, "Carnes Cross Roads 2 - 009 - 1751": 0, "Brooksville #1 - 106 - 890": 0, "Four Mile - 136 - 794": 0, "Burgess #3 - 219 - 885": 0, "Sedgefield 2 - 082 - 1706": 0, "Garden City #2 - 139 - 1565": 0, "Coastal Lane #1 - 116 - 787": 0, "Mt. Pleasant 14 - 314 - 348": 0, "Mt. Pleasant 26 - 326 - 357": 0, "Socastee #4 - 202 - 858": 0, "Lake Park #2 - 228 - 1568": 0, "Mt. Pleasant 4 - 304 - 370": 0, "Mt. Pleasant 20 - 320 - 353": 0, "Mt. Pleasant 1 - 301 - 344": 0, "Mt. Pleasant 36 - 336 - 364": 0, "Moncks Corner 4 - 034 - 1775": 0, "Stratford 1 - 044 - 1736": 0, "Sangaree 2 - 039 - 1728": 0, "Emerald Forest #1 - 130 - 888": 0, "Seventy Eight - 072 - 1727": 0, "Myrtle Trace - 170 - 869": 0, "South Dillon - 003 - 1803": 0, "Singletary - 031 - 1359": 0, "Tramway - 083 - 1771": 0, "Yeaman's Club - 102 - 1777": 0, "Nixons Xroads #2 - 175 - 850": 0, "Nesmith - 024 - 1368": 0, "Mt. Pleasant 25 - 325 - 352": 0, "Nixons Xroads #1 - 174 - 892": 0, "Kensington - 116 - 613": 0, "Mt. Pleasant 16 - 316 - 286": 0, "Cedar Swamp - 004 - 1369": 0, "Charleston 7 - 207 - 280": 0, "Centenary - 003 - 1036": 0, "Floydale - 019 - 1798": 0, "Bethel - 103 - 610": 0, "Hickory Hill - 146 - 798": 0, "Morrisville - 021 - 1370": 0, "Central - 005 - 1700": 0, "Sullivans Island - 032 - 267": 0, "Pleasant View - 186 - 893": 0, "Mt. Pleasant 22 - 322 - 354": 0, "Cobblestone - 092 - 1769": 0, "Bermuda - 010 - 1809": 0, "Lambert Town - 107 - 620": 0, "Mt. Pleasant 10 - 310 - 350": 0, "Gallivants Ferry - 137 - 795": 0, "Leon - 159 - 807": 0, "Mt. Pleasant 29 - 329 - 359": 0, "Pawley's Island No. 3 - 124 - 636": 0, "Leo - 042 - 1519": 0, "Huger - 026 - 1712": 0, "Racepath #1 - 189 - 827": 0, "Hannah - 034 - 1521": 0, "Macedonia - 029 - 1715": 0, "Socastee #2 - 200 - 857": 0, "Bloomingvale - 002 - 1372": 0, "Kemper - 007 - 1800": 0, "Tilly Swamp - 210 - 873": 0, "Westview 1 - 050 - 1739": 0, "Dunes #1 - 124 - 875": 0, "Foster Creek 2 - 077 - 1763": 0, "Dunes #2 - 125 - 851": 0, "Mt. Pleasant 18 - 318 - 349": 0, "Mt. Pleasant 37 - 337 - 365": 0, "White Oak - 215 - 844": 0, "Green Sea - 143 - 797": 0, "Mt. Pleasant 30 - 330 - 360": 0, "Carver's Bay - 106 - 633": 0, "Brownway - 107 - 784": 0, "Daniel Island 4 - 062 - 1746": 0, "Mt. Pleasant 11 - 311 - 345": 0, "Lake View - 006 - 1811": 0, "Sea Winds - 197 - 847": 0, "East Conway - 127 - 2261": 0, "Lake City No. 3 - 040 - 1538": 0, "Murrell's Inlet No. 1 - 117 - 631": 0, "Sedgefield 1 - 081 - 1764": 0, "Jamestown - 151 - 802": 0, "Fox Bank - 067 - 1756": 0, "Surfside #2 - 205 - 836": 0, "Jet Port #2 - 154 - 868": 0, "Indiantown - 013 - 1367": 0, "Cherry Grove #1 - 113 - 786": 0, "Barrineau - 002 - 504": 1, "Mcallister Mill - 045 - 1539": 1, "Oak Pointe 3 - 468 - 1201": 1, "Elgin No. 6 - 127 - 2059": 1, "Sunset - 141 - 1305": 1, "Clio - 009 - 1046": 1, "Ebenezer No. 2 - 011 - 1549": 1, "Woodrow - 022 - 909": 1, "Causeway Branch 2 - 158 - 1315": 1, "Wilder - 131 - 1296": 1, "Hartsville No. 9 - 041 - 558": 1, "Dalzell 2 - 106 - 1330": 1, "Hickory Hill - 010 - 901": 1, "Tans Bay - 059 - 1556": 1, "Rice Creek 1 - 485 - 1215": 1, "Hillcrest - 103 - 1275": 1, "Salters - 029 - 1377": 1, "Cades - 003 - 1358": 1, "Pageland No. 2 - 020 - 473": 1, "Carolina - 014 - 1807": 1, "Simpson - 015 - 592": 1, "Pocotaligo 1 - 132 - 1297": 1, "Palmetto - 033 - 553": 1, "Monticello - 462 - 1230": 1, "Winnsboro No. 2 - 019 - 596": 1, "Cassatt - 115 - 2067": 1, "West Florence 1 - 063 - 1555": 1, "Cedar Creek - 007 - 899": 1, "Florence Ward 15 - 030 - 1502": 1, "Back Swamp - 001 - 1517": 1, "Crosswell - 125 - 1292": 1, "Florence Ward 12 - 028 - 1557": 1, "Florence Ward 9 - 025 - 1514": 1, "Blythewood 3 - 408 - 1213": 1, "Brownsville - 004 - 1041": 1, "Darlington No. 1 - 007 - 539": 1, "Brightsville - 003 - 1040": 1, "Doby's Mill - 119 - 2071": 1, "Cheraw No. 2 - 008 - 461": 1, "Carmel - 004 - 1582": 1, "Millwood - 137 - 1302": 1, "Harmony - 007 - 496": 1, "Timmonsville 1 - 060 - 1548": 1, "Hampton Park - 124 - 1291": 1, "Florence Ward 4 - 019 - 1504": 1, "Ridge View 1 - 487 - 1236": 1, "Salem - 053 - 1535": 1, "Hartsville No. 6 - 018 - 563": 1, "Parkway 2 - 474 - 1243": 1, "Riversprings 3 - 493 - 1197": 1, "Elgin No. 3 - 124 - 2069": 1, "Middendorf - 016 - 478": 1, "Salterstown - 116 - 1286": 1, "Green Swamp - 118 - 1329": 1, "Bates - 134 - 1299": 1, "Darlington No. 2 - 008 - 540": 1, "Sumter High 1 - 140 - 1304": 1, "Midway - 019 - 1586": 1, "Bishopville 3 - 005 - 897": 1, "Alvin - 001 - 1786": 1, "South Florence 1 - 056 - 1564": 1, "University - 033 - 1572": 1, "Mitford - 011 - 601": 1, "Darlington No. 5 - 011 - 542": 1, "Society Hill - 036 - 554": 1, "Lane - 018 - 1379": 1, "Rice Creek 2 - 486 - 1237": 1, "Oak Pointe 1 - 466 - 1180": 1, "Mount Vernon - 022 - 1360": 1, "Mayesville - 108 - 1278": 1, "Blairs - 002 - 582": 1, "Jenkinsville - 007 - 600": 1, "Turkey Creek - 114 - 1284": 1, "Courthouse - 011 - 476": 1, "Center Grove-Winzo - 006 - 455": 1, "Black Creek - 003 - 466": 1, "E Bennettsville - 012 - 1049": 1, "Greenwood - 033 - 1507": 1, "Riversprings 2 - 492 - 1196": 1, "Bridge Creek - 413 - 1217": 1, "Marion No. 2 - 006 - 1025": 1, "Manville - 013 - 904": 1, "Coles Crossroads - 005 - 1508": 1, "Loring - 126 - 1293": 1, "Lydia - 027 - 550": 1, "Lugoff No. 4 - 135 - 2078": 1, "Florence Ward 2 - 017 - 1505": 1, "W Bennettsville - 013 - 1050": 1, "Blythewood 2 - 407 - 1210": 1, "Ebenezer No. 3 - 012 - 1552": 1, "Lake Swamp - 024 - 549": 1, "Indian Branch - 022 - 547": 1, "Dwight - 007 - 1575": 1, "Longleaf - 454 - 1252": 1, "Mccrays Mill 1 - 111 - 1281": 1, "Folsom Park - 117 - 1287": 1, "Springville 2 - 505 - 1198": 1, "Minturn - 016 - 1797": 1, "Quinby - 052 - 1516": 1, "Hartsville No. 1 - 013 - 567": 1, "Rabon's X Roads - 143 - 2056": 1, "Causeway Branch 1 - 138 - 1326": 1, "Savage-Glover - 133 - 1298": 1, "Turkey Creek - 021 - 908": 1, "Lemira - 127 - 1319": 1, "Florence Ward 14 - 029 - 1562": 1, "Rich Hill - 022 - 1585": 1, "Mt. Clio - 014 - 900": 1, "Antioch - 001 - 537": 1, "Savannah Grove - 054 - 1550": 1, "Shiloh - 024 - 467": 1, "Consolidated Number 5 - 028 - 1501": 1, "Auburn - 002 - 538": 1, "Camden No. 5 - 111 - 2075": 1, "Burnt Branch - 005 - 561": 1, "Blythewood 1 - 406 - 1212": 1, "Florence Ward 6 - 022 - 1560": 1, "Ebenezer No. 1 - 010 - 1551": 1, "New Market - 031 - 565": 1, "Effingham - 013 - 1545": 1, "Riverside - 023 - 1602": 1, "Thomas Sumter - 154 - 1311": 1, "Jefferson - 014 - 475": 1, "Mars Bluff No. 1 - 043 - 1531": 1, "Kingstree No.1 - 014 - 1381": 1, "Whites Gardens - 154 - 2052": 1, "Oak Pointe 2 - 467 - 1200": 1, "Chesterfield Ave - 005 - 1579": 1, "Hebron - 010 - 1354": 1, "Oakland Plantation 2 - 110 - 1280": 1, "Valhalla - 508 - 1219": 1, "Cheraw No. 3 - 009 - 463": 1, "Springdale - 150 - 2062": 1, "Cartersville - 003 - 1546": 1, "Pee Dee - 022 - 470": 1, "Riverwalk - 494 - 1186": 1, "South Florence 2 - 057 - 1506": 1, "Morris College - 123 - 1290": 1, "Quicks X Roads - 008 - 1045": 1, "Lamar No. 1 - 025 - 559": 1, "Darlington No. 3 - 038 - 556": 1, "Mcbee - 015 - 479": 1, "Bloomville - 004 - 494": 1, "Dudley-Mangum - 012 - 472": 1, "Florence Ward 8 - 024 - 1563": 1, "Macedonia 2 - 096 - 1787": 1, "Darlington No. 6 - 040 - 557": 1, "St. Matthews - 020 - 915": 1, "Manning No. 5 - 015 - 491": 1, "Gooch's Cross Roads - 010 - 1580": 1, "Dutch Fork 3 - 421 - 1194": 1, "Black Creek-Clyde - 004 - 566": 1, "E. Camden-Hermitage - 121 - 2070": 1, "College Park - 041 - 1603": 1, "Hartsville No. 7 - 019 - 568": 1, "Russellville - 037 - 1722": 1, "Trio - 033 - 1374": 1, "Horatio - 102 - 1274": 1, "South Red Bay - 130 - 1295": 1, "Lancaster West - 017 - 1604": 1, "Marion North - 007 - 1026": 1, "Black River - 001 - 1356": 1, "Manning No. 4 - 014 - 490": 1, "South Winnsboro - 016 - 593": 1, "Sellers - 010 - 1028": 1, "Hartsville No. 4 - 016 - 564": 1, "Harmony - 009 - 1373": 1, "Delaine - 142 - 1306": 1, "Green Swamp 2 - 157 - 1321": 1, "Swan Lake - 122 - 1289": 1, "Lake Carolina - 451 - 1211": 1, "Mulberry - 115 - 1285": 1, "Dalzell 1 - 105 - 1323": 1, "Mccoll - 010 - 1047": 1, "High Hill - 021 - 546": 1, "Ridge View 2 - 488 - 1216": 1, "Cheraw No. 4 - 010 - 462": 1, "Stone Hill - 129 - 1294": 1, "Latta - 004 - 1794": 1, "Camden No. 1 - 107 - 2061": 1, "Marion No. 1 - 005 - 1024": 1, "Gates Ford - 130 - 2048": 1, "East Mccoll - 011 - 1048": 1, "Unity - 025 - 1570": 1, "Bethune - 103 - 2066": 1, "Ashland/Stokes Bridge - 001 - 912": 1, "Temperance - 011 - 1029": 1, "N East Mullins - 015 - 1033": 1, "Lugoff No. 1 - 132 - 2045": 1, "Oak Grove-Sardis - 047 - 1534": 1, "Carlisle - 005 - 1343": 1, "Kelly Mill - 448 - 1209": 1, "West Florence 2 - 064 - 1558": 1, "Peak - 034 - 1499": 1, "Elgin No. 5 - 126 - 2047": 1, "St. Stephen 1 - 042 - 1724": 1, "Jacksonham - 013 - 1601": 1, "Earles - 006 - 1375": 1, "Evergreen - 015 - 1523": 1, "Hickory Ridge - 009 - 588": 1, "Hamer - 012 - 1808": 1, "Mayewood - 113 - 1283": 1, "Barrows Mill - 003 - 499": 1, "Mechanicsville - 028 - 551": 1, "Grants Mill - 013 - 477": 1, "Elgin No. 4 - 125 - 2050": 1, "Manning No. 3 - 013 - 487": 1, "Parkway 3 - 475 - 1242": 1, "Ballentine 1 - 402 - 1178": 1, "Winnsboro No. 1 - 018 - 595": 1, "Spring Hill - 501 - 1171": 1, "West Dillon - 002 - 1802": 1, "Olanta - 048 - 1533": 1, "Pageland No. 1 - 019 - 474": 1, "Pontiac 1 - 483 - 1250": 1, "South Lynchburg - 012 - 903": 1, "Ashwood - 002 - 894": 1, "Wilson Hall - 149 - 1309": 1, "Eadytown - 016 - 1704": 1, "Heath Springs - 011 - 1587": 1, "Friendfield - 031 - 1522": 1, "Wallace - 007 - 1044": 1, "Hartsville No. 5 - 017 - 544": 1, "Bookman - 409 - 1238": 1, "Greeleyville - 008 - 1378": 1, "Centerville - 003 - 583": 1, "Oswego - 107 - 1277": 1, "Second Mill - 121 - 1288": 1, "Lancaster East - 016 - 1573": 1, "Bishopville 2 - 004 - 896": 1, "Oak Grove - 017 - 1793": 1, "Privateer - 147 - 1324": 1, "South Liberty - 136 - 1301": 1, "Zion - 012 - 1030": 1, "Old Friarsgate - 433 - 1182": 1, "Schrocks Mill/Lucknow - 016 - 910": 1, "Ebenezer 1 - 148 - 1316": 1, "Birnie - 135 - 1300": 1, "Spring Hill - 024 - 1571": 1, "New Zion - 016 - 501": 1, "Swift Creek - 037 - 555": 1, "Ruby - 023 - 458": 1, "Maybinton - 025 - 1500": 1, "Palmetto Park - 119 - 1313": 1, "Jamestown - 027 - 1713": 1, "Cowards No. 2 - 007 - 1543": 1, "Lugoff No. 3 - 134 - 2077": 1, "Little Rock - 015 - 1796": 1, "Hicks - 008 - 503": 1, "Ballentine 2 - 403 - 1199": 1, "Delmae No. 1 - 008 - 1554": 1, "Claussen - 004 - 1530": 1, "Lebanon - 010 - 589": 1, "Round Top - 495 - 1245": 1, "Andrews - 101 - 616": 1, "Camden No. 5-A - 112 - 2073": 1, "Riversprings 1 - 491 - 1181": 1, "Manning No. 1 - 011 - 493": 1, "Red Hill - 005 - 1042": 1, "Pergamos - 026 - 1355": 1, "Bethel - 003 - 562": 1, "Camp Creek - 003 - 1574": 1, "Shaylor's Hill - 149 - 2058": 1, "Elgin No. 1 - 122 - 2072": 1, "Scranton - 055 - 1542": 1, "Cross - 011 - 1702": 1, "Horeb-Glenn - 008 - 587": 1, "Florence Ward 10 - 026 - 1512": 1, "East Dillon - 001 - 1805": 1, "Bunrs-Downs - 120 - 1314": 1, "Spring Hill - 018 - 906": 1, "Salt Pond - 147 - 2053": 1, "Mallet Hill - 456 - 1226": 1, "Elim-Glenwood - 014 - 1536": 1, "S Bennettsville - 014 - 1051": 1, "Cypress - 008 - 911": 1, "Tatum - 006 - 1043": 1, "Angelus-Catarrh - 001 - 456": 1, "Brocks Mill - 004 - 468": 1, "Rattlesnake Springs - 015 - 905": 1, "Buffalo - 105 - 2068": 1, "Florence Ward 1 - 016 - 1509": 1, "Springville 1 - 504 - 1172": 1, "Oakland Plantation 1 - 104 - 1276": 1, "Hartsville No. 8 - 020 - 545": 1, "Manning No. 2 - 012 - 492": 1, "Oates - 032 - 552": 1, "Elgin No. 2 - 123 - 2049": 1, "Jordan - 010 - 482": 1, "Turbeville - 023 - 502": 1, "Bishopville 4 - 006 - 898": 1, "Delmae No. 2 - 009 - 1553": 1, "Darlington No. 4 - 010 - 541": 1, "Hobkirk's Hill - 109 - 2064": 1, "Pleasant Hill - 020 - 1583": 1, "Sardina-Gable - 019 - 500": 1, "Ousleydale - 018 - 465": 1, "Kelleytown - 023 - 548": 1, "Patrick - 021 - 469": 1, "Florence Ward 7 - 023 - 1559": 1, "St. Charles - 019 - 907": 1, "Pamplico No. 1 - 049 - 1524": 1, "Greenbrier - 005 - 585": 1, "Manchester Forest - 144 - 1307": 1, "Shaw - 153 - 1328": 1, "Suttons - 032 - 1380": 1, "Riverdale - 146 - 2054": 1, "Charlotte Thompson - 117 - 2074": 1, "Ionia - 011 - 902": 1, "Gilbert - 032 - 1510": 1, "Westville - 152 - 2055": 1, "Hyde Park - 012 - 1577": 1, "Salem - 109 - 1279": 1, "Blenheim - 002 - 1039": 1, "Bonneau - 003 - 1698": 1, "High Hill - 035 - 1520": 1, "Mccrays Mill 2 - 139 - 1303": 1, "Dutchmans Creek - 022 - 602": 1, "Antioch - 102 - 2063": 1, "Florence Ward 11 - 027 - 1503": 1, "Bay Springs - 002 - 464": 1, "Winnsboro Mills - 017 - 594": 1, "Douglas - 006 - 1581": 1, "Friarsgate 1 - 431 - 1183": 1, "Elgin - 008 - 1578": 1, "Florence Ward 3 - 018 - 1511": 1, "Marion South - 008 - 1037": 1, "Mars Bluff No. 2 - 044 - 1532": 1, "Cash - 005 - 471": 1, "Harbison 2 - 440 - 1188": 1, "Liberty Hill - 131 - 2057": 1, "Andrews Outside - 102 - 617": 1, "St.John - 112 - 1282": 1, "Home Branch - 009 - 489": 1, "Feasterville - 004 - 584": 1, "Dovesville - 012 - 543": 1, "Sandy Bay - 030 - 1357": 1, "Brookgreen - 002 - 1513": 1, "Sandlapper - 497 - 1249": 1, "Lynchburg - 012 - 913": 1, "Kershaw North - 014 - 1588": 1, "N Bennettsville - 015 - 1052": 1, "Lamar No. 2 - 026 - 560": 1, "Marion West - 009 - 1027": 1, "Pomaria - 035 - 1498": 1, "Camden No. 2 & 3 - 108 - 2065": 1, "Oakland - 013 - 1806": 1, "Malvern Hill - 140 - 2051": 1, "Spaulding - 058 - 1515": 1, "Cherryvale - 143 - 1322": 1, "Cowards No. 1 - 006 - 1544": 1, "Rembert - 101 - 1273": 1, "Sumter High 2 - 155 - 1312": 1, "Mt. Groghan - 017 - 457": 1, "Timmonsville 2 - 061 - 1547": 1, "Lugoff No. 2 - 133 - 2046": 1, "Florence Ward 5 - 020 - 1561": 1, "Antioch - 001 - 1576": 1, "Pontiac 2 - 484 - 1251": 1, "Magnolia-Harmony - 128 - 1320": 1, "Ebenezer 2 - 156 - 1318": 1, "St. Paul - 152 - 1327": 1, "Kershaw South - 015 - 1589": 1, "Elliott - 009 - 914": 1, "Moultrie - 069 - 1778": 1, "Oakdale - 025 - 498": 1, "Dutch Fork 2 - 420 - 1179": 1, "Lynwood Drive - 018 - 1584": 1, "Cheraw No. 1 - 007 - 460": 1, "Bishopville 1 - 003 - 895": 1, "Spectrum - 151 - 1310": 1, "Wilson Foreston - 024 - 497": 1, "Dutch Fork 4 - 422 - 1195": 1, "Adamsville - 001 - 1038": 1, "Alcolu - 001 - 495": 1, "St. Stephen 2 - 043 - 1725": 1, "Estates - 425 - 1218": 1, "Bonneau Beach - 004 - 1699": 1, "Dutch Fork 1 - 419 - 1177": 1, "Longcreek - 453 - 1246": 1, "Monticello - 012 - 599": 1, "Snow Hill-Vaughn - 025 - 459": 1, "Camden No. 6 - 113 - 2076": 1, "Airport - 101 - 2060": 1, "Parkway 1 - 473 - 1244": 1, "Ridgeway - 014 - 591": 1, "New Holly - 005 - 1795": 1, "Greenville 3 - 203 - 711": 2, "Greenville 25 - 225 - 698": 2, "Anderson 1/2 - 075 - 1667": 2, "Hammond School - 036 - 1647": 2, "Carolina - 242 - 2225": 2, "Wellington - 340 - 709": 2, "Greenville 20 - 220 - 671": 2, "Return - 014 - 2007": 2, "Forest Acres - 141 - 1989": 2, "Abel - 104 - 1959": 2, "Gluck Mill - 032 - 1680": 2, "Rock Springs - 144 - 1952": 2, "Ranch Creek - 361 - 755": 2, "Pelham Falls - 294 - 2244": 2, "Greenville 5 - 205 - 696": 2, "South Pickens - 123 - 1947": 2, "Mauldin 3 - 278 - 651": 2, "Altamont Forest - 231 - 737": 2, "Riverside - 362 - 752": 2, "Cedar Grove - 018 - 1642": 2, "Chestnut Hills - 243 - 677": 2, "Leawood - 272 - 724": 2, "Anderson 4/1 - 080 - 1656": 2, "Donaldson - 250 - 650": 2, "Anderson 3/2 - 079 - 1678": 2, "Dove Tree - 251 - 691": 2, "Holly Springs - 118 - 1941": 2, "Taylors - 328 - 731": 2, "Keowee - 007 - 2024": 2, "Tri County - 160 - 1950": 2, "La France - 043 - 1631": 2, "Hopewell - 040 - 1671": 2, "Westcliffe - 341 - 2216": 2, "Maple Creek - 274 - 2246": 2, "Shiloh - 019 - 2026": 2, "Rock Mill - 057 - 1617": 2, "Town Creek - 165 - 1669": 2, "Lakeside - 087 - 1628": 2, "Reedy Fork - 299 - 641": 2, "Enoree - 256 - 729": 2, "Toney Creek - 065 - 2218": 2, "Iva - 041 - 1673": 2, "Seneca 2 - 030 - 2023": 2, "Mcallister - 161 - 1972": 2, "Avon - 233 - 720": 2, "Edgewood Station B - 092 - 1664": 2, "Monaview - 284 - 708": 2, "Glenview - 132 - 1670": 2, "Southside - 318 - 669": 2, "Mount Tabor - 046 - 1614": 2, "Greenville 4 - 204 - 707": 2, "Friendship - 005 - 2025": 2, "Jackson Mill - 042 - 1619": 2, "Ebenezer - 254 - 2208": 2, "Craytonville - 023 - 1681": 2, "Lakeview - 270 - 718": 2, "Norris - 112 - 1976": 2, "Belmont - 236 - 660": 2, "Tokeena-Providence - 022 - 2015": 2, "Seneca 4 - 032 - 2021": 2, "University - 102 - 1958": 2, "Rock Spring - 058 - 1650": 2, "Pumpkintown - 119 - 2205": 2, "Pickensville - 139 - 1990": 2, "Lawrence Chapel - 111 - 1955": 2, "Pope Field - 158 - 1988": 2, "Bishop's Branch - 013 - 1616": 2, "North Pointe - 050 - 1646": 2, "Tamassee - 021 - 1998": 2, "Nine Forks - 152 - 2207": 2, "Sheffield - 159 - 1973": 2, "South Fant - 000 - 1679": 2, "Issaqueena - 107 - 1960": 2, "Townville - 066 - 1612": 2, "Poinsett - 297 - 728": 2, "West Liberty - 129 - 1977": 2, "Mckissick - 148 - 1994": 2, "Greenville 21 - 221 - 678": 2, "Flat Rock - 028 - 1622": 2, "Edwards Forest - 255 - 730": 2, "Long Creek - 358 - 756": 2, "Brushy Creek - 017 - 1638": 2, "Spring Forest - 319 - 701": 2, "Pike - 110 - 1956": 2, "Northwood - 288 - 717": 2, "Anderson 6/2 - 085 - 1658": 2, "Georges Creek - 147 - 1953": 2, "Holly Springs - 006 - 2001": 2, "Welcome - 339 - 681": 2, "Suber Mill - 323 - 753": 2, "Concrete - 021 - 1636": 2, "Griffin - 120 - 1944": 2, "Greenville 28 - 228 - 697": 2, "Mission - 283 - 695": 2, "Utica - 023 - 2009": 2, "Slater Marietta - 317 - 2206": 2, "Greenville 18 - 218 - 673": 2, "Clear Creek - 245 - 740": 2, "Crescent Hill - 154 - 1995": 2, "Five Forks - 027 - 1632": 2, "Newry-Corinth - 001 - 2010": 2, "Saluda - 306 - 2215": 2, "Woodside - 137 - 1982": 2, "Anderson 4/2 - 081 - 1654": 2, "Royal Oaks - 305 - 655": 2, "Glassy Mountain - 125 - 1943": 2, "Furman - 262 - 736": 2, "Westminster 2 - 027 - 2017": 2, "Greenville 23 - 223 - 674": 2, "South Union - 020 - 2011": 2, "Simpson - 136 - 1983": 2, "Westminster 1 - 026 - 2016": 2, "Anderson 2/2 - 077 - 1660": 2, "Greenville 19 - 219 - 666": 2, "Ravenel - 003 - 2008": 2, "Aiken - 230 - 689": 2, "Easley - 140 - 1991": 2, "Homeland Park - 038 - 1653": 2, "East Pickens - 124 - 1987": 2, "West Savannah - 069 - 1618": 2, "Green Pond Station A - 033 - 1625": 2, "Shirley's Store - 061 - 1645": 2, "Locust Hill - 357 - 739": 2, "Anderson 2/1 - 076 - 1661": 2, "Mt Airy - 094 - 1637": 2, "Arial Mill - 134 - 1985": 2, "Del Norte - 248 - 713": 2, "Oakway - 012 - 2014": 2, "Fork No 2 - 030 - 1611": 2, "West Pelzer - 068 - 2221": 2, "Williamston - 071 - 2219": 2, "Rices Creek - 128 - 1978": 2, "Anderson 1/1 - 074 - 1666": 2, "Pebble Creek - 293 - 733": 2, "Crossroads - 150 - 1942": 2, "West Central - 108 - 1964": 2, "North Central - 109 - 1966": 2, "Earles Grove - 002 - 2013": 2, "Grove - 266 - 2226": 2, "Crestview - 142 - 1971": 2, "Brushy Creek - 138 - 1970": 2, "Salem - 016 - 1999": 2, "Bountyland - 011 - 2005": 2, "Broadview - 012 - 1652": 2, "North Liberty - 155 - 1980": 2, "Eastside - 253 - 723": 2, "Mountain Creek - 285 - 735": 2, "Greenville 27 - 227 - 704": 2, "Rock Hill - 302 - 706": 2, "Greenville 16 - 216 - 679": 2, "Belle Meade - 234 - 659": 2, "Greenville 6 - 206 - 700": 2, "Centerville Station A - 019 - 1626": 2, "Greenville 8 - 208 - 686": 2, "Walhalla 1 - 024 - 2019": 2, "Starr - 063 - 1620": 2, "Greenville 29 - 229 - 668": 2, "Mt. Pleasant - 345 - 653": 2, "Broadway - 016 - 1649": 2, "Albert R. Lewis - 117 - 1948": 2, "Mountain Creek - 047 - 1623": 2, "Greenville 22 - 222 - 683": 2, "Wright's School - 073 - 1674": 2, "Greenville 17 - 217 - 682": 2, "West Pickens - 122 - 1946": 2, "Williamston Mill - 072 - 1641": 2, "Centerville Station B - 091 - 1627": 2, "Six Mile Mountain - 114 - 1974": 2, "Berea - 237 - 716": 2, "Bowling Green - 015 - 1648": 2, "Center Rock - 157 - 1624": 2, "Timberlake - 331 - 715": 2, "Tanglewood - 327 - 2214": 2, "South Central - 153 - 1965": 2, "Laurel Ridge - 271 - 738": 2, "Denver-Sandy Springs - 024 - 1630": 2, "Morrison - 103 - 1961": 2, "Pendleton - 053 - 1615": 2, "Belton - 011 - 1672": 2, "Brookglenn - 240 - 726": 2, "Anderson 6/1 - 084 - 1662": 2, "White Plains - 070 - 1639": 2, "Wade Hampton - 336 - 725": 2, "West Union - 028 - 2004": 2, "Anderson 5/B - 083 - 1655": 2, "Calhoun - 105 - 1957": 2, "Pendleton - 156 - 1968": 2, "Skelton - 127 - 1986": 2, "Sitton - 143 - 1951": 2, "Edgewood Station A - 025 - 1663": 2, "Long Creek - 008 - 1996": 2, "Lenhart - 163 - 1992": 2, "Greenville 7 - 207 - 692": 2, "Simpsonville - 062 - 2224": 2, "Appleton-Equinox - 009 - 1659": 2, "Fork No 1 - 029 - 1613": 2, "Lowndesville - 013 - 1683": 2, "Zion - 132 - 1969": 2, "Paris Mountain - 292 - 732": 2, "Neal's Creek - 049 - 1651": 2, "Silverleaf - 309 - 722": 2, "Varennes - 086 - 1629": 2, "Powdersville - 121 - 2223": 2, "Hunt Meadows - 164 - 1635": 2, "Seneca 3 - 031 - 2022": 2, "Walhalla 2 - 025 - 2018": 2, "Hall - 035 - 1621": 2, "Greenville 14 - 214 - 684": 2, "Palmetto - 291 - 699": 2, "Mountain Rest - 009 - 1997": 2, "Jennings Mill - 269 - 2204": 2, "Flat Rock - 131 - 1967": 2, "Sugar Creek - 324 - 714": 2, "Cedar Rock - 126 - 1993": 2, "Mauldin 2 - 277 - 675": 2, "Saluda - 145 - 2213": 2, "Three And Twenty - 064 - 1634": 2, "Smith Grove - 133 - 1981": 2, "Mountain View - 116 - 1949": 2, "Woodmont - 343 - 643": 2, "Feaster - 257 - 688": 2, "Thornblade - 329 - 705": 2, "Greenville 1 - 201 - 710": 2, "Granite Creek - 351 - 2245": 2, "Sulphur Springs - 325 - 2209": 2, "Greenville 24 - 224 - 690": 2, "Vinland - 149 - 2211": 2, "Six Mile - 113 - 1954": 2, "Stamp Creek - 017 - 2002": 2, "Clemson - 106 - 1963": 2, "Canebrake - 241 - 719": 2, "Madison - 010 - 2000": 2, "Westside - 342 - 703": 2, "Piedmont - 054 - 2222": 2, "Richland - 015 - 2006": 2, "Anderson 3/1 - 078 - 1657": 2, "Cox's Creek - 093 - 1668": 2, "Botany Woods - 239 - 721": 2, "Fruit Mountain - 157 - 1984": 2, "Belton Annex - 111 - 1643": 2, "Melton - 045 - 1633": 2, "Greenville 26 - 226 - 694": 2, "Stone Church - 101 - 1962": 2, "Sevier - 308 - 727": 2, "Devenger - 249 - 702": 2, "Mauldin 1 - 276 - 663": 2, "Piercetown - 055 - 1640": 2, "North Pickens - 121 - 1945": 2, "Conestee - 246 - 652": 2, "Moore Creek - 359 - 646": 2, "Crosswell - 146 - 2212": 2, "Hammond Annex - 136 - 1665": 2, "Boiling Springs - 238 - 712": 2, "Seneca 1 - 029 - 2020": 2, "Mauldin 4 - 279 - 656": 2, "East Liberty - 130 - 1979": 2, "Greenville 10 - 210 - 693": 2, "Fair Play - 004 - 2012": 2, "Praters Creek - 115 - 1975": 2, "New Hope - 018 - 2003": 2, "Stone Valley - 321 - 734": 2, "Dacusville - 151 - 2210": 2, "St. Andrews 22 - 522 - 387": 3, "Tranquil 3 - 104 - 1885": 3, "Grahamville 2 - 008 - 2039": 3, "Deer Park 1A - 102 - 332": 3, "Bluffton 2B - 306 - 89": 3, "Clemson 2 - 089 - 1834": 3, "Bluffton 1D - 304 - 79": 3, "James Island 11 - 411 - 261": 3, "Greenwave - 046 - 1848": 3, "Hanahan 1 - 020 - 1708": 3, "St. Andrews 18 - 518 - 326": 3, "Ridgeland 1 - 006 - 2030": 3, "Walterboro No. 3 - 031 - 530": 3, "Windsor 2 - 110 - 1878": 3, "Seabrook 2 - 162 - 17": 3, "Irongate - 058 - 1857": 3, "Ridgeland 2 - 007 - 2038": 3, "Burton 1A - 110 - 0": 3, "Peeples - 017 - 534": 3, "Hilton Head 4D - 210 - 33": 3, "Moncks Corner 1 - 031 - 1717": 3, "Kiawah Island - 180 - 237": 3, "Westview 3 - 052 - 1726": 3, "St. Andrews 10 - 510 - 294": 3, "Hilton Head 7A - 216 - 72": 3, "James Island 8A - 407 - 341": 3, "Ridgeland 3 - 005 - 2029": 3, "St. Andrews 13 - 513 - 383": 3, "Charleston 3 - 203 - 2044": 3, "North Charleston 30 - 630 - 251": 3, "St. Andrews 27 - 527 - 391": 3, "Folly Beach 1 - 184 - 258": 3, "Bells - 002 - 510": 3, "Charleston 12 - 212 - 296": 3, "Foster Creek 1 - 076 - 1759": 3, "James Island 5A - 403 - 265": 3, "Bluffton 5B - 318 - 78": 3, "Tranquil - 040 - 1870": 3, "Mossy Oaks 1A - 140 - 11": 3, "New River - 000 - 92": 3, "Westview 4 - 075 - 1740": 3, "Trolley - 039 - 1868": 3, "Port Royal 2 - 151 - 15": 3, "St. Andrews 11 - 511 - 381": 3, "Deer Park 2C - 106 - 254": 3, "North Charleston 16 - 616 - 304": 3, "St. Andrews 6 - 506 - 329": 3, "James Island 15 - 415 - 246": 3, "Sun City 3 - 363 - 62": 3, "Rose Hill - 316 - 88": 3, "Charleston 14 - 214 - 275": 3, "North Charleston 2 - 602 - 301": 3, "North Charleston 10 - 610 - 308": 3, "Saul Dam - 037 - 1826": 3, "Canadys - 005 - 511": 3, "North Charleston 18 - 618 - 371": 3, "Daufuskie - 200 - 26": 3, "North Charleston 26 - 626 - 376": 3, "Port Royal 1 - 150 - 14": 3, "Flowertown 3 - 108 - 1887": 3, "St. Andrews 28 - 528 - 392": 3, "Deer Park 2A - 104 - 253": 3, "Coastal 2 - 079 - 1863": 3, "Hilton Head 1A - 201 - 27": 3, "St. Andrews 23 - 523 - 388": 3, "Hilton Head 15B - 228 - 44": 3, "Saint Helena 1C - 182 - 23": 3, "Petits - 018 - 509": 3, "Edisto - 007 - 516": 3, "Grover - 028 - 1818": 3, "North Charleston 25 - 625 - 303": 3, "Folly Beach 2 - 185 - 266": 3, "North Charleston 28 - 628 - 257": 3, "Sun City 2 - 362 - 61": 3, "St. Andrews 29 - 529 - 390": 3, "St. Andrews 25 - 525 - 389": 3, "Briarwood 3 - 087 - 1861": 3, "Edisto Island - 173 - 231": 3, "St. Andrews 33 - 533 - 395": 3, "Burton 1D - 179 - 49": 3, "Coastal - 038 - 1864": 3, "St. Andrews 7 - 507 - 325": 3, "Deer Park 2B - 105 - 334": 3, "Hilton Head 4C - 209 - 32": 3, "Wildcat Trail - 101 - 1772": 3, "Irongate 3 - 097 - 1856": 3, "St. Andrews 14 - 514 - 379": 3, "Sheldon 2 - 171 - 20": 3, "St. Andrews 32 - 532 - 322": 3, "Pinopolis - 036 - 1721": 3, "Johns Island 3A - 443 - 239": 3, "Clemson 3 - 090 - 1835": 3, "Lincoln - 074 - 1877": 3, "Ashborough East - 061 - 1858": 3, "Stratford 4 - 047 - 1735": 3, "Wadmalaw Island 1 - 174 - 233": 3, "Coosaw - 071 - 1875": 3, "Walterboro No. 6 - 037 - 520": 3, "St. Andrews 1 - 501 - 295": 3, "James Island 19 - 419 - 245": 3, "St. Andrews 17 - 517 - 316": 3, "Daniel Island 2 - 013 - 1703": 3, "Flowertown - 042 - 1831": 3, "Moss Creek - 308 - 76": 3, "Central - 070 - 1840": 3, "Hilton Head 15A - 227 - 43": 3, "Saint Helena 2C - 185 - 25": 3, "Johns Island 2 - 442 - 342": 3, "Burton 2C - 115 - 4": 3, "Walterboro No. 2 - 030 - 536": 3, "St. Andrews 30 - 530 - 320": 3, "Sheldon 1 - 170 - 19": 3, "St. George No. 1 - 027 - 1817": 3, "Oakbrook - 076 - 1871": 3, "Bluffton 4D - 317 - 83": 3, "Stallsville - 052 - 1852": 3, "Brandymill - 067 - 1860": 3, "Miles/Jamison - 075 - 1865": 3, "Hilton Head 3 - 206 - 29": 3, "James Island 1B - 401 - 338": 3, "Spann - 055 - 1846": 3, "Ladys Island 3C - 187 - 55": 3, "Hilton Head 5B - 212 - 35": 3, "Whitesville 1 - 059 - 1765": 3, "Stratford 2 - 045 - 1743": 3, "North Charleston 6 - 606 - 310": 3, "Archdale 2 - 081 - 1880": 3, "Yemassee - 013 - 769": 3, "Beaufort 1 - 101 - 52": 3, "Moncks Corner 3 - 033 - 1719": 3, "Hardeeville 2 - 028 - 2028": 3, "North Charleston 1 - 601 - 311": 3, "Coosaw 2 - 091 - 1874": 3, "James Island 7 - 406 - 340": 3, "Hilton Head 4B - 208 - 31": 3, "St. Andrews 15 - 515 - 318": 3, "Bluffton 2E - 315 - 81": 3, "St. Andrews 16 - 516 - 384": 3, "Hudson Mill - 011 - 508": 3, "James Island 9 - 409 - 243": 3, "St. Andrews 37 - 537 - 2203": 3, "Palmetto Bluff - 001 - 84": 3, "North Charleston 7 - 607 - 312": 3, "Brandymill 2 - 085 - 1866": 3, "James Island 20 - 420 - 244": 3, "North Summerville 2 - 100 - 1837": 3, "North Charleston 9 - 609 - 314": 3, "Burton 3 - 116 - 51": 3, "James Island 13 - 413 - 262": 3, "Bluffton 2D - 314 - 77": 3, "North Charleston 29 - 629 - 255": 3, "Briarwood - 068 - 1854": 3, "Hilton Head 10 - 222 - 39": 3, "Sniders - 027 - 526": 3, "Levy - 014 - 2036": 3, "Saint Helena 1A - 180 - 21": 3, "Dorchester - 049 - 1838": 3, "Sawmill Branch - 078 - 1847": 3, "Ashborough West 2 - 083 - 1881": 3, "Clemson - 044 - 1836": 3, "Coastal 3 - 080 - 1862": 3, "James Island 10 - 410 - 337": 3, "Bluffton 1A - 301 - 82": 3, "Johns Island 4 - 445 - 238": 3, "Ladys Island 3A - 134 - 9": 3, "Burton 2A - 113 - 2": 3, "Flowertown 2 - 093 - 1832": 3, "Ladson - 132 - 315": 3, "Coosawhatchie - 002 - 2034": 3, "Butternut - 069 - 1839": 3, "Sun City 5 - 364 - 64": 3, "North Charleston 23 - 623 - 323": 3, "Walterboro No. 4 - 032 - 519": 3, "St. Andrews 31 - 531 - 319": 3, "St. Andrews 21 - 521 - 382": 3, "Sun City 4 - 361 - 63": 3, "North Creek - 086 - 1754": 3, "Wolf Creek - 034 - 524": 3, "Hilton Head 12 - 224 - 41": 3, "Walterboro No. 1 - 029 - 515": 3, "North Charleston 13 - 613 - 306": 3, "North Charleston 22 - 622 - 374": 3, "Sun City 7 - 366 - 66": 3, "Johns Island 1B - 441 - 343": 3, "Hilton Head 5C - 213 - 70": 3, "Charleston 13 - 213 - 272": 3, "Green Pond - 008 - 527": 3, "Hardeeville 1 - 012 - 2043": 3, "Burton 1B - 111 - 1": 3, "Hilton Head 11 - 223 - 40": 3, "North Charleston 5 - 605 - 377": 3, "North Charleston 12 - 612 - 307": 3, "Hilton Head 6 - 214 - 36": 3, "Sandy Pointe - 003 - 91": 3, "Ladys Island 2B - 133 - 90": 3, "Newington - 047 - 1849": 3, "Seabrook 3 - 163 - 18": 3, "Archdale - 050 - 1879": 3, "Peniel - 019 - 513": 3, "James Island 22 - 422 - 240": 3, "St. Andrews 12 - 512 - 380": 3, "Cane Bay South - 091 - 1781": 3, "Bluffton 4A - 310 - 2041": 3, "Lincolnville - 110 - 249": 3, "Irongate 2 - 096 - 1855": 3, "Yellow House - 064 - 1780": 3, "Sun City 1 - 360 - 60": 3, "Seabrook 1 - 161 - 48": 3, "James Island 6 - 405 - 339": 3, "Charleston 16 - 216 - 273": 3, "Central 2 - 088 - 1841": 3, "Hilton Head 9A - 220 - 67": 3, "Grahamville 1 - 026 - 2027": 3, "James Island 3 - 402 - 242": 3, "St. Andrews 34 - 534 - 393": 3, "Hilton Head 2A - 203 - 74": 3, "Ritter - 020 - 518": 3, "St. Pauls 3 - 463 - 402": 3, "Charleston 18 - 218 - 282": 3, "King's Grant - 073 - 1873": 3, "Wadmalaw Island 2 - 175 - 234": 3, "Sun City 6 - 365 - 65": 3, "Ladys Island 2C - 186 - 8": 3, "Hilton Head 4A - 207 - 30": 3, "Patriot - 077 - 1888": 3, "Charleston 15 - 215 - 283": 3, "Ladys Island 1B - 131 - 6": 3, "St. Andrews 8 - 508 - 327": 3, "James Island 8B - 408 - 241": 3, "Old 52 - 070 - 1720": 3, "North Charleston 14 - 614 - 305": 3, "St. Andrews 26 - 526 - 317": 3, "Germantown - 045 - 1844": 3, "Burton 1C - 112 - 50": 3, "North Charleston 17 - 617 - 302": 3, "Belfair - 315 - 58": 3, "Hilton Head 7B - 217 - 37": 3, "St. Andrews 9 - 509 - 328": 3, "North Charleston 24 - 624 - 250": 3, "Stokes - 026 - 514": 3, "Town Of Seabrook - 181 - 232": 3, "North Charleston 11 - 611 - 309": 3, "St. Andrews 24 - 524 - 321": 3, "Johns Island 3B - 444 - 235": 3, "Westview 2 - 051 - 1741": 3, "St. Andrews 5 - 505 - 397": 3, "Indian Field - 054 - 1813": 3, "James Island 14 - 414 - 260": 3, "Charleston 17 - 217 - 297": 3, "Reevesville - 029 - 1812": 3, "Dale Lobeco - 160 - 16": 3, "Hanahan 4 - 023 - 1762": 3, "Bluffton 1C - 303 - 46": 3, "Ashley River - 063 - 1889": 3, "Saint Helena 2B - 183 - 24": 3, "Daniel Island 3 - 061 - 1744": 3, "Hilton Head 8 - 219 - 68": 3, "Cypress 2 - 107 - 1882": 3, "North Charleston 4 - 604 - 300": 3, "Mossy Oaks 1B - 141 - 12": 3, "North Charleston 8 - 608 - 378": 3, "Hendersonville - 009 - 528": 3, "Bluffton 2C - 307 - 80": 3, "Charleston 11 - 211 - 271": 3, "Moncks Corner 2 - 032 - 1718": 3, "Mashawville - 015 - 529": 3, "Ashborough West - 062 - 1867": 3, "Hilton Head 1B - 202 - 28": 3, "Knightsville - 043 - 1830": 3, "James Island 1A - 400 - 259": 3, "Wassamassaw 1 - 048 - 1773": 3, "Sun City - 015 - 2035": 3, "Saint Helena 1B - 181 - 22": 3, "Ladys Island 2A - 132 - 7": 3, "Tranquil 2 - 102 - 1869": 3, "North Charleston 21 - 621 - 375": 3, "Deer Park 1B - 103 - 333": 3, "Hilton Head 14 - 226 - 42": 3, "Cane Bay - 065 - 1774": 3, "Hilton Head 2C - 205 - 73": 3, "Deer Park 3 - 107 - 252": 3, "Cane Bay North - 090 - 1779": 3, "Sidneys - 024 - 525": 3, "King's Grant 2 - 098 - 1872": 3, "Hanahan 2 - 021 - 1709": 3, "Beaufort 3 - 103 - 53": 3, "Ashborough East 2 - 082 - 1859": 3, "Bluffton 5A - 313 - 47": 3, "Horse Pen - 010 - 533": 3, "Hanahan 3 - 022 - 1760": 3, "North Summerville - 056 - 1890": 3, "Mossy Oaks 2 - 142 - 13": 3, "St. Andrews 19 - 519 - 386": 3, "Charleston 1 - 201 - 276": 3, "Carolina - 048 - 1891": 3, "James Island 12 - 412 - 264": 3, "Briarwood 2 - 086 - 1853": 3, "St. Andrews 35 - 535 - 396": 3, "Bowman 2 - 122 - 1070": 3, "Charleston 21 - 221 - 299": 3, "Chechessee 2 - 121 - 2040": 3, "Ladys Island 1A - 130 - 5": 3, "St. Andrews 20 - 520 - 385": 3, "North Charleston 3 - 603 - 324": 3, "Ruffin - 023 - 523": 3, "Cypress - 072 - 1829": 3, "Round O - 021 - 517": 3, "St. Andrews 4 - 504 - 398": 3, "St. Pauls 1 - 460 - 400": 3, "North Charleston 27 - 627 - 256": 3, "Hilton Head 13 - 225 - 69": 3, "Ladys Island 3B - 135 - 10": 3, "Windsor - 064 - 1876": 3, "Charleston 19 - 219 - 331": 3, "Walterboro No. 5 - 036 - 535": 3, "Bluffton 2A - 305 - 59": 3, "Hilton Head 5A - 211 - 34": 3, "Cane Bay East - 089 - 1767": 3, "Bluffton 4B - 311 - 86": 3, "James Island 17 - 417 - 247": 3, "Beaufort 2 - 102 - 54": 3, "Okatie - 034 - 2042": 3, "Oakbrook 2 - 109 - 1884": 3, "Bluffton 3 - 309 - 57": 3, "Charleston 20 - 220 - 298": 3, "Wassamassaw 2 - 049 - 1755": 3, "North Charleston 15 - 615 - 313": 3, "Tillman - 010 - 2037": 3, "St. Andrews 2 - 502 - 330": 3, "Bacons Bridge 2 - 105 - 1886": 3, "Saint Helena 2A - 183 - 56": 3, "Sun City 8 - 367 - 75": 3, "Coosaw 3 - 106 - 1883": 3, "Live Oak - 095 - 1768": 3, "Hilton Head 2B - 204 - 71": 3, "Burton 2B - 114 - 3": 3, "Newington 2 - 099 - 1850": 3, "Edisto Beach - 035 - 505": 3, "Bluffton 1B - 302 - 45": 3, "James Island 5B - 404 - 263": 3, "North Charleston 19 - 619 - 372": 3, "Tupperway - 057 - 1843": 3, "St. Andrews 3 - 503 - 293": 3, "St. Andrews 36 - 536 - 394": 3, "North Charleston 20 - 620 - 373": 3, "Greenhurst - 060 - 1851": 3, "Chechessee 1 - 120 - 87": 3, "Ridgeville 2 - 101 - 1892": 3, "Tupperway 2 - 103 - 1842": 3, "Dorchester 2 - 092 - 1845": 3, "Hilton Head 9B - 221 - 38": 3, "Johns Island 1A - 440 - 236": 3, "Charleston 5 - 205 - 269": 3, "Bluffton 4C - 312 - 85": 3, "Silver Bluff - 061 - 125": 4, "Ward 11 - 111 - 1115": 4, "Greenview - 436 - 1149": 4, "Furman - 010 - 776": 4, "St. George No. 2 - 026 - 1816": 4, "Williams - 033 - 522": 4, "Holly Hill 1 - 134 - 1082": 4, "Givhans 2 - 094 - 1823": 4, "Aiken No. 4 - 004 - 96": 4, "Early Branch - 005 - 768": 4, "Fairwold - 427 - 1145": 4, "Lebanon - 028 - 1714": 4, "Elloree 2 - 129 - 1077": 4, "Woodfield - 515 - 1235": 4, "East Denmark - 004 - 187": 4, "Olympia - 470 - 1160": 4, "Levels No. 72 - 072 - 150": 4, "Sandhill - 080 - 993": 4, "South Forest Acres - 430 - 1147": 4, "Keels 2 - 446 - 1241": 4, "Midland Valley No. 51 - 051 - 142": 4, "Suburban 9 - 119 - 1067": 4, "Orangeburg Wd 10 - 110 - 1060": 4, "Grenadier - 058 - 972": 4, "Kearse - 008 - 191": 4, "St. Pauls 2A - 461 - 399": 4, "Horrell Hill - 443 - 1152": 4, "Cordova 2 - 152 - 1100": 4, "Aiken No. 3 - 003 - 95": 4, "Suburban 3 - 113 - 1105": 4, "Keels 1 - 445 - 1228": 4, "Midland Valley No. 71 - 071 - 122": 4, "Davis Station - 006 - 481": 4, "Cedar Creek No. 64 - 064 - 154": 4, "Ward 8 - 108 - 1112": 4, "Perry - 031 - 128": 4, "Whittaker - 149 - 1097": 4, "Friendship - 008 - 212": 4, "North Springs 2 - 464 - 1220": 4, "Ward 9 - 109 - 1113": 4, "Healing Springs - 010 - 205": 4, "Ward 15 - 115 - 1119": 4, "Bethel - 001 - 220": 4, "Eutawville 2 - 131 - 1079": 4, "Sleepy Hollow No. 65 - 065 - 158": 4, "Ward 33 - 133 - 1134": 4, "Chalk Hill - 038 - 953": 4, "Suburban 4 - 114 - 1062": 4, "Pineridge #2 - 091 - 2255": 4, "Suburban 2 - 112 - 1061": 4, "Rosinville - 025 - 1814": 4, "Bowman 1 - 121 - 1069": 4, "Jacksonboro - 012 - 506": 4, "Edmund #1 - 017 - 932": 4, "Gifford - 021 - 770": 4, "Keenan - 447 - 1154": 4, "Aiken No. 5 - 005 - 97": 4, "Orangeburg Wd 3 - 103 - 1102": 4, "Orangeburg Wd 5 - 105 - 1055": 4, "Sandstone No. 70 - 070 - 170": 4, "W Columbia No 4 - 047 - 961": 4, "Arcadia - 400 - 1136": 4, "Orangeburg Wd 1 - 101 - 1053": 4, "Ward 22 - 122 - 1126": 4, "Ward 16 - 116 - 1120": 4, "Six Points No. 35 - 035 - 165": 4, "W Columbia No 1 - 044 - 958": 4, "Harleyville - 030 - 1820": 4, "Montmorenci No. 22 - 022 - 162": 4, "Martin - 005 - 2252": 4, "Bonnett - 009 - 775": 4, "North Bamberg - 013 - 196": 4, "Ward 25 - 125 - 1129": 4, "Gloverville - 015 - 144": 4, "South Aiken No. 76 - 076 - 160": 4, "Springfield - 147 - 1095": 4, "Barnwell No. 1 - 001 - 197": 4, "Hollow Creek - 053 - 161": 4, "Holly Hill 2 - 133 - 1081": 4, "Williston No. 3 - 015 - 209": 4, "Ward 20 - 120 - 1124": 4, "Barnwell No. 3 - 003 - 199": 4, "College Acres - 013 - 105": 4, "Aiken No. 47 - 047 - 147": 4, "Oakwood - 469 - 1159": 4, "China Springs - 011 - 103": 4, "Lynwood - 019 - 123": 4, "Sycamore - 006 - 181": 4, "Spring Valley West - 503 - 1223": 4, "Pennington 2 - 477 - 1247": 4, "Cayce Ward No.2 - 036 - 951": 4, "Elko - 007 - 203": 4, "Midway - 009 - 213": 4, "Grays - 001 - 2033": 4, "Sandy Run - 025 - 940": 4, "Mill Creek - 461 - 1158": 4, "Ridgewood - 489 - 1163": 4, "Mt Hebron - 079 - 992": 4, "Ward 19 - 119 - 1123": 4, "Gaston #1 - 026 - 941": 4, "Pelion #2 - 083 - 996": 4, "Cayce Ward No.3 - 037 - 952": 4, "Furman - 150 - 1325": 4, "Ulmer - 007 - 182": 4, "Cayce Ward No.1 - 035 - 950": 4, "Maple Cane - 014 - 532": 4, "Hopkins 1 - 441 - 1204": 4, "Orangeburg Wd 6 - 106 - 1056": 4, "Harmony - 009 - 573": 4, "Center Hill - 003 - 214": 4, "Skyland - 499 - 1176": 4, "Johnston No.2 - 005 - 571": 4, "Meadowlake - 458 - 1232": 4, "Eastover - 423 - 1143": 4, "Hampton Courthouse No.2 - 003 - 763": 4, "Orangeburg Wd 8 - 108 - 1058": 4, "Lykesland - 455 - 1155": 4, "Ward 3 - 103 - 1108": 4, "Suburban 6 - 116 - 1064": 4, "Fairfax #2 - 004 - 183": 4, "St. Pauls 6 - 466 - 248": 4, "Gadsden - 434 - 1203": 4, "Williston No. 1 - 013 - 207": 4, "Millbrook - 020 - 148": 4, "Cromer - 032 - 947": 4, "Ward 4 - 104 - 1109": 4, "Aiken No. 2 - 002 - 94": 4, "Brandon 2 - 411 - 1208": 4, "Shiloh - 034 - 136": 4, "Rivers Mill - 015 - 765": 4, "College Place - 415 - 1140": 4, "Edenwood - 031 - 946": 4, "Redds Branch - 057 - 151": 4, "Summerton No. 3 - 022 - 486": 4, "Emmanuel Church - 014 - 929": 4, "Ardincaple - 401 - 1137": 4, "Red Bank South #2 - 092 - 1006": 4, "Westover - 030 - 945": 4, "West Denmark - 012 - 195": 4, "North Forest Acres - 429 - 1254": 4, "Red Bank South #1 - 013 - 928": 4, "Gem Lakes No. 60 - 060 - 169": 4, "St Davids - 078 - 991": 4, "White Pond - 042 - 126": 4, "Suburban 7 - 117 - 1065": 4, "Bluff - 405 - 1138": 4, "Scotia - 011 - 2262": 4, "Meadowfield - 457 - 1157": 4, "Gregg Park - 437 - 1150": 4, "Midway - 460 - 1234": 4, "Mcentire - 459 - 1156": 4, "Govan - 005 - 188": 4, "Spring Valley - 502 - 1224": 4, "Aiken No. 1 - 001 - 93": 4, "Clearwater - 012 - 104": 4, "Ward 14 - 114 - 1118": 4, "Ehrhardt - 003 - 186": 4, "Talatha - 037 - 155": 4, "Cameron - 002 - 221": 4, "Lincolnshire - 452 - 1231": 4, "Ornageburg Wd 7 - 107 - 1057": 4, "Orangeburg Wd 4 - 104 - 1104": 4, "Allendale #1 - 001 - 178": 4, "Cooper - 416 - 1141": 4, "Hunting Creek - 444 - 1153": 4, "Congaree #2 - 077 - 990": 4, "Swansea #1 - 024 - 939": 4, "Congaree #1 - 039 - 954": 4, "Couchton - 056 - 152": 4, "Beech Hill 2 - 084 - 1827": 4, "Tabernacle - 036 - 130": 4, "Bethel - 120 - 1068": 4, "Riverside - 490 - 1175": 4, "Levels No. 52 - 052 - 149": 4, "Berea-Smoaks - 039 - 531": 4, "Sandy Run - 011 - 216": 4, "North 2 - 139 - 1087": 4, "Cottageville - 006 - 512": 4, "North Springs 1 - 463 - 1221": 4, "Hopkins 2 - 442 - 1205": 4, "Fort Motte - 007 - 223": 4, "Santee 1 - 145 - 1093": 4, "Killian - 449 - 1214": 4, "Blackville No. 2 - 006 - 202": 4, "Ward 30 - 130 - 1131": 4, "Old Barnwell Rd - 005 - 920": 4, "Gardendale - 051 - 965": 4, "Quail Hollow - 021 - 936": 4, "Springdale - 042 - 957": 4, "Kingswood - 450 - 1193": 4, "North Springs 3 - 465 - 1240": 4, "Six Points No. 46 - 046 - 164": 4, "Windsor No. 43 - 043 - 134": 4, "Hilda - 011 - 211": 4, "Pine Lakes 2 - 480 - 1169": 4, "Garnett - 006 - 777": 4, "Horse Gall - 014 - 773": 4, "Hampton - 438 - 1151": 4, "Varnville - 004 - 764": 4, "Hitchcock No. 66 - 066 - 146": 4, "Summerton No. 2 - 021 - 483": 4, "Kline - 009 - 204": 4, "Aiken No. 6 - 006 - 98": 4, "Blackville No. 1 - 005 - 201": 4, "Willow Springs - 049 - 115": 4, "Brunson - 001 - 761": 4, "St. Matthews - 012 - 219": 4, "Windsor No. 82 - 082 - 173": 4, "Ward 26 - 126 - 1206": 4, "Oakwood - 088 - 1000": 4, "Ward 5 - 105 - 1110": 4, "Ward 6 - 106 - 1253": 4, "Suburban 8 - 118 - 1066": 4, "Crocket-Miley - 017 - 766": 4, "Colston - 001 - 184": 4, "Pinewood - 481 - 1162": 4, "Montmorenci No. 78 - 078 - 163": 4, "South Beltline - 500 - 1165": 4, "Leaphart Road - 029 - 944": 4, "Pine Forest - 059 - 157": 4, "Pine Lakes 1 - 479 - 1161": 4, "Lone Star - 008 - 224": 4, "Salley - 032 - 127": 4, "Woodland Hills - 052 - 966": 4, "Woods - 008 - 2253": 4, "Hammond No. 48 - 048 - 176": 4, "Trenholm Road - 506 - 1166": 4, "Orangeburg Wd 9 - 109 - 1059": 4, "Warrenville - 041 - 145": 4, "Panola - 018 - 485": 4, "Cope - 126 - 1074": 4, "Creston - 004 - 222": 4, "Langley - 018 - 143": 4, "Bacons Bridge - 066 - 1833": 4, "Jackson - 017 - 124": 4, "Graniteville - 016 - 141": 4, "Johnston No.1 - 004 - 572": 4, "Santee 2 - 146 - 1094": 4, "Gillisonville - 003 - 2031": 4, "South Bamberg - 011 - 194": 4, "Cummings - 018 - 767": 4, "Saluda River - 041 - 956": 4, "Pinewood - 145 - 1317": 4, "Limestone 2 - 150 - 1098": 4, "Wildewood - 514 - 1225": 4, "Ward 32 - 132 - 1133": 4, "Woodlands - 516 - 1167": 4, "Bolentown - 142 - 1090": 4, "Barnwell No. 2 - 002 - 198": 4, "Hightower's Mill - 006 - 189": 4, "Four Hole - 031 - 1819": 4, "Hunter's Chapel - 007 - 190": 4, "Neeses-Livingston - 137 - 1085": 4, "Ward 12 - 112 - 1116": 4, "St. Pauls 4 - 464 - 404": 4, "Dennyside - 417 - 1233": 4, "Trinity - 507 - 1168": 4, "Brookdale - 125 - 1073": 4, "Edgewood - 424 - 1144": 4, "Suburban 1 - 111 - 1103": 4, "W Columbia No 2 - 045 - 959": 4, "Fairfax #1 - 003 - 180": 4, "Cayce Ward 2-A - 055 - 969": 4, "Vance - 148 - 1096": 4, "Nix - 138 - 1086": 4, "Ward - 040 - 137": 4, "Gem Lakes No. 77 - 077 - 167": 4, "Pineland - 004 - 2032": 4, "Brandon 1 - 410 - 1207": 4, "Ward 7 - 107 - 1111": 4, "Dixie - 005 - 218": 4, "Ward 23 - 123 - 1127": 4, "Westminster - 512 - 1174": 4, "Hopewell - 016 - 772": 4, "Briarwood - 412 - 1227": 4, "Barnwell No. 4 - 004 - 200": 4, "Polo Road - 482 - 1239": 4, "Ward 34 - 134 - 1135": 4, "Ward 31 - 131 - 1132": 4, "Branchville 2 - 124 - 1072": 4, "Calvary - 005 - 484": 4, "Sandstone No. 79 - 079 - 168": 4, "Summerton No. 1 - 020 - 480": 4, "Four Holes - 132 - 1080": 4, "Suburban 5 - 115 - 1063": 4, "Rowesville - 144 - 1092": 4, "Ward 10 - 110 - 1114": 4, "Murph Hill - 010 - 215": 4, "Hilton Cross Rd - 024 - 1710": 4, "Elloree 1 - 154 - 1101": 4, "W Columbia No 3 - 046 - 960": 4, "Eutawville 1 - 130 - 1078": 4, "East Forest Acres - 428 - 1146": 4, "Paxville - 017 - 488": 4, "Pineridge #1 - 043 - 2254": 4, "Mack-Edisto - 023 - 938": 4, "Ward 2 - 102 - 1107": 4, "Little Swamp - 009 - 192": 4, "Limestone 1 - 136 - 1084": 4, "Beech Island - 008 - 100": 4, "Rosses - 033 - 1821": 4, "St. Pauls 2B - 462 - 401": 4, "Anderson Pond No. 69 - 069 - 159": 4, "Webber - 511 - 1170": 4, "Swansea #2 - 082 - 995": 4, "Edisto - 002 - 185": 4, "Ashton-Lodge - 038 - 507": 4, "Fairlawn - 426 - 1229": 4, "Valley State Park - 509 - 1222": 4, "Allendale #2 - 002 - 179": 4, "Snelling - 012 - 206": 4, "Satchelford - 498 - 1164": 4, "Ward 24 - 124 - 1128": 4, "Caughman Road - 414 - 1139": 4, "Indian Field 2 - 095 - 1815": 4, "Estill - 007 - 774": 4, "Providence - 143 - 1091": 4, "Dentsville - 418 - 1142": 4, "Ward 13 - 113 - 1117": 4, "Garners - 435 - 1148": 4, "Pine Hill - 151 - 1099": 4, "Srs - 016 - 210": 4, "North 1 - 140 - 1088": 4, "Pineview - 053 - 967": 4, "Shaws Fork - 033 - 135": 4, "Givhans - 035 - 1824": 4, "Srs - 000 - 177": 4, "Ward 1 - 101 - 1106": 4, "Ward 29 - 129 - 1130": 4, "Ward 18 - 118 - 1122": 4, "Black Creek - 019 - 771": 4, "Levels No. 83 - 083 - 174": 4, "Branchville 1 - 123 - 1071": 4, "Bath - 007 - 99": 4, "Williston No. 2 - 014 - 208": 4, "Hammond No. 81 - 081 - 175": 4, "Delemars - 036 - 1825": 4, "Pocotaligo 2 - 146 - 1308": 4, "Wagener - 039 - 129": 4, "Hook's Store - 040 - 955": 4, "Springdale South - 074 - 987": 4, "St. Pauls 5 - 465 - 403": 4, "Hampton Courthouse No.1 - 002 - 762": 4, "Beech Hill - 041 - 1828": 4, "Ridgeville - 034 - 1822": 4, "Rice Patch - 022 - 521": 4, "South Aiken No. 75 - 075 - 153": 4, "Fall Branch - 006 - 217": 4, "Olar - 010 - 193": 4, "New Ellenton - 023 - 156": 4, "Cordova 1 - 127 - 1075": 4, "Jamison - 135 - 1083": 4, "Edisto - 128 - 1076": 4, "White Knoll - 065 - 978": 4, "New Holland - 024 - 131": 4, "Ward 21 - 121 - 1125": 4, "St. Andrews - 496 - 1173": 4, "Ward 17 - 117 - 1121": 4, "Pennington 1 - 476 - 1248": 4, "Orangeburg Wd 2 - 102 - 1054": 4, "Norway - 141 - 1089": 4, "Gaston #2 - 075 - 988": 4, "Sharpe's Hill - 027 - 942": 4, "Lake Murray #1 - 003 - 918": 5, "Harris - 010 - 1899": 5, "Enoree First Baptist - 034 - 2134": 5, "Pelham Fire Station - 061 - 2233": 5, "Delmar - 003 - 1268": 5, "Modoc - 014 - 1013": 5, "Wellford Fire Station - 097 - 2138": 5, "Lexington No. 1 - 033 - 948": 5, "Reidville Elementary - 064 - 2232": 5, "Grandiflora Glen - 004 - 1904": 5, "Prosperity Outside - 051 - 1608": 5, "Park Road #2 - 090 - 1004": 5, "Canaan - 015 - 2154": 5, "Simpsonville 1 - 310 - 648": 5, "Clyde - 002 - 1266": 5, "Barksdale-Narine - 010 - 2097": 5, "Waterloo - 027 - 2110": 5, "Mims - 002 - 917": 5, "Biltmore Pines - 042 - 1925": 5, "Graze Branch - 352 - 754": 5, "Lower Lake - 036 - 1927": 5, "Dunklin - 252 - 2230": 5, "Sparrows Point - 363 - 759": 5, "Greenwood Mill - 033 - 1907": 5, "Barr Road #1 - 056 - 970": 5, "Ascauga Lake No. 84 - 084 - 121": 5, "Willington - 004 - 1011": 5, "Woodruff Leisure Center - 001 - 2132": 5, "Woodruff Fire Station - 027 - 2231": 5, "Mauldin 6 - 281 - 657": 5, "Quail Valley - 054 - 968": 5, "N. Augusta No. 55 - 055 - 108": 5, "Holly Tree - 355 - 760": 5, "Whitewell - 513 - 1191": 5, "Abbeville No. 1 - 001 - 1693": 5, "Oakland - 031 - 1485": 5, "Bailey - 007 - 2107": 5, "Circle Creek - 244 - 2243": 5, "Round Hill - 019 - 934": 5, "Pineview - 296 - 2200": 5, "Belvedere No. 9 - 009 - 101": 5, "Bradley - 022 - 1919": 5, "Chappells - 013 - 1475": 5, "Mount Olive - 030 - 2100": 5, "Challedon - 049 - 963": 5, "Angel Oak's Crossing - 049 - 1938": 5, "Levi's Knoll - 003 - 1929": 5, "Laurens 6 - 006 - 2090": 5, "Hall's Store - 011 - 1692": 5, "Due West - 010 - 1689": 5, "Saluda No. 2 - 018 - 1258": 5, "Newberry Ward 6 - 006 - 1488": 5, "Gilbert - 007 - 922": 5, "Riley - 031 - 1896": 5, "Honea Path - 039 - 1676": 5, "R.D. Anderson Vocational - 056 - 2130": 5, "Kitti Wake - 067 - 980": 5, "Trenton No.2 - 013 - 578": 5, "Cooks - 022 - 2089": 5, "Parkridge 2 - 472 - 1202": 5, "Mountain Laurel - 045 - 1924": 5, "Ware Place - 369 - 2229": 5, "Cokesbury - 016 - 1897": 5, "Abbeville No. 3 - 003 - 1687": 5, "Mccormick No. 1 - 006 - 1016": 5, "Boiling Springs - 016 - 931": 5, "Troy - 023 - 1918": 5, "Kinards-Jalapa - 019 - 1490": 5, "Dutchman Shores - 063 - 976": 5, "High Point - 037 - 1644": 5, "Fox Creek No. 58 - 058 - 119": 5, "Vaucluse - 038 - 139": 5, "Amicks Ferry - 061 - 1007": 5, "Baker Creek - 346 - 2228": 5, "Stonewood - 034 - 1940": 5, "Ninety Six - 012 - 1914": 5, "Fountain Inn 1 - 259 - 2202": 5, "Brewerton-Princeton - 033 - 2101": 5, "Ridge Road - 010 - 925": 5, "N. Augusta No. 80 - 080 - 172": 5, "Mauldin 7 - 282 - 664": 5, "Anderson Mill Elementary - 121 - 2188": 5, "Ashley River Run - 005 - 1908": 5, "Woodruff Elementary - 135 - 2184": 5, "Bells Crossing - 235 - 661": 5, "Monticello - 002 - 1020": 5, "Carolina Heights - 010 - 102": 5, "Clinton 3 - 017 - 2102": 5, "Clinton 1 - 012 - 2079": 5, "Providence Church - 068 - 981": 5, "Mt. Willing - 012 - 1263": 5, "Trenton No.1 - 006 - 579": 5, "Fairview - 015 - 1495": 5, "Friendship - 031 - 2217": 5, "Holy Communion - 083 - 2194": 5, "Newberry Ward 5 - 005 - 1480": 5, "Loblolly Pines - 001 - 1910": 5, "Poplar Springs Fire Station - 062 - 2146": 5, "Parson's Mill - 048 - 1933": 5, "Bush River - 062 - 975": 5, "Edgefield No.2 - 002 - 576": 5, "N. Augusta No. 67 - 067 - 109": 5, "Pinecrest - 037 - 1903": 5, "Barker's Creek-Mcadams - 010 - 1677": 5, "Dreher Island - 084 - 1008": 5, "Misty Lakes - 045 - 120": 5, "Ora-Lanford - 024 - 2086": 5, "Coronaca - 017 - 1939": 5, "Hickory Tavern - 031 - 2096": 5, "Liberty - 041 - 1916": 5, "Greenbriar - 353 - 758": 5, "Abbeville No. 4 - 004 - 1685": 5, "Clark's Hill - 015 - 1012": 5, "River Bluff - 096 - 979": 5, "Airport - 028 - 1901": 5, "Fairhope Ferry - 007 - 1926": 5, "Cedarcrest - 087 - 999": 5, "St. Michael - 059 - 973": 5, "Carolina Springs - 093 - 1001": 5, "Beatty Road - 404 - 1190": 5, "Beech Springs Intermediate - 115 - 2137": 5, "Gable Middle School - 010 - 2157": 5, "Richland - 015 - 1261": 5, "Mt. Bethel-Garmany - 027 - 1489": 5, "Chapin - 028 - 943": 5, "Newberry Ward 2 - 002 - 1486": 5, "Maddens - 011 - 2106": 5, "Maxwellton Pike - 038 - 1928": 5, "Donald's - 009 - 1690": 5, "Whitmire Outside - 050 - 1492": 5, "Barr Road #2 - 089 - 1005": 5, "Kilgore Farms - 356 - 665": 5, "N. Augusta No. 54 - 054 - 166": 5, "Pelion #1 - 022 - 937": 5, "Edmund #2 - 081 - 994": 5, "Seven Oaks - 009 - 924": 5, "Black Rock - 002 - 1342": 5, "Laurens 3 - 003 - 2109": 5, "Ward - 020 - 1260": 5, "Parkridge 1 - 471 - 1185": 5, "Allie's Crossing - 046 - 1915": 5, "Murraywood - 060 - 974": 5, "N. Augusta No. 68 - 068 - 113": 5, "Owings - 019 - 2087": 5, "Union Ward 3 - 020 - 1334": 5, "Ekom - 029 - 2093": 5, "Chiquola Mill - 020 - 1675": 5, "Saluda No. 1 - 017 - 1262": 5, "Pilgrim Church - 064 - 977": 5, "Belvedere No. 44 - 044 - 116": 5, "Lexington No. 2 - 034 - 949": 5, "Lebanon - 014 - 1684": 5, "Bethany Wesleyan - 117 - 2141": 5, "Buffalo Box 1 - 004 - 1338": 5, "Lincreek - 086 - 998": 5, "Abbeville No. 2 - 002 - 1694": 5, "Hope's Ferry - 006 - 1923": 5, "Hodges - 015 - 1931": 5, "Leesville - 012 - 927": 5, "Oak Grove - 030 - 132": 5, "Old Lexington - 085 - 997": 5, "Fork Shoals - 258 - 2199": 5, "Laurens 5 - 005 - 2108": 5, "Fountain Inn 2 - 260 - 2201": 5, "Monetta - 021 - 133": 5, "Ninety Six Mill - 013 - 1922": 5, "Lexington No. 3 - 070 - 983": 5, "Hillcrest - 354 - 654": 5, "Trinity Presbyterian - 142 - 2142": 5, "Simpsonville 2 - 311 - 647": 5, "Neely Farms - 287 - 639": 5, "Walnut Springs - 337 - 2242": 5, "Travelers Rest Baptist - 036 - 2149": 5, "Cold Springs - 008 - 1688": 5, "Whitmire City - 049 - 1493": 5, "O'Neal - 030 - 1494": 5, "Irmo - 048 - 962": 5, "Calhoun Falls - 007 - 1682": 5, "Mayson - 010 - 1255": 5, "Newberry Ward 3 - 003 - 1482": 5, "Cavins Hobbysville - 017 - 2131": 5, "Clinton 2 - 013 - 2081": 5, "Lake Murray #2 - 076 - 989": 5, "Sardis - 019 - 1267": 5, "Epworth - 024 - 1921": 5, "Mimosa Crest - 035 - 1934": 5, "Hollywood - 008 - 1272": 5, "Plum Branch - 010 - 1018": 5, "Bee's Ferry - 002 - 1909": 5, "Holly - 007 - 1270": 5, "Oakview - 289 - 685": 5, "N. Augusta No. 25 - 025 - 106": 5, "Emerald - 027 - 2260": 5, "New Market - 026 - 1913": 5, "Wheeland - 048 - 1496": 5, "Little Mountain - 023 - 1610": 5, "Centennial - 001 - 1259": 5, "Higgins/Zoar - 006 - 1271": 5, "Wattsville - 009 - 2104": 5, "Brunson - 011 - 570": 5, "Pine Grove - 478 - 1189": 5, "Pleasant Grove - 014 - 1269": 5, "N. Augusta No. 28 - 028 - 110": 5, "Georgetown - 019 - 1902": 5, "Cross Keys - 006 - 1341": 5, "Newberry Ward 4 - 004 - 1481": 5, "Greenwood High - 018 - 1930": 5, "Mauldin 5 - 280 - 672": 5, "Belvedere No. 74 - 074 - 117": 5, "N. Augusta No. 26 - 026 - 111": 5, "Stoney Hill - 040 - 1479": 5, "Laco - 011 - 1917": 5, "Simpsonville 3 - 312 - 645": 5, "Bridge Fork - 347 - 658": 5, "Whitehall - 050 - 964": 5, "Keowee - 012 - 1696": 5, "Graham's Glen - 050 - 1937": 5, "Westside - 008 - 575": 5, "Broadmouth - 006 - 1691": 5, "Summit - 011 - 926": 5, "Fox Creek No. 73 - 073 - 118": 5, "Long Branch - 025 - 2091": 5, "Jones - 018 - 2103": 5, "Fairview - 020 - 935": 5, "Bethany - 008 - 1015": 5, "Roebuck Elementary - 065 - 2156": 5, "Faith Church - 066 - 1009": 5, "Pond Branch - 008 - 923": 5, "Raintree - 298 - 637": 5, "Union Ward 4 Box 2 - 022 - 1351": 5, "East Buffalo - 007 - 1350": 5, "Antreville - 005 - 1686": 5, "Park Road #1 - 073 - 986": 5, "Gideon's Way - 047 - 2259": 5, "Smithville - 015 - 1695": 5, "Youngs - 023 - 2111": 5, "Parksville - 013 - 1014": 5, "Marshall Oaks - 043 - 1911": 5, "Mount Horeb - 004 - 919": 5, "River Ridge Elementary - 137 - 2182": 5, "Breezy Hill - 050 - 140": 5, "Glendale - 009 - 1936": 5, "Clinton Mill - 034 - 2099": 5, "Eureka - 014 - 138": 5, "Walden - 510 - 1192": 5, "Simpsonville 6 - 315 - 640": 5, "Sycamore - 326 - 649": 5, "Merriweather No.1 - 007 - 577": 5, "Martins-Poplar Springs - 028 - 2098": 5, "Simpsonville 4 - 313 - 644": 5, "Lexington No. 4 - 071 - 984": 5, "Ridge Spring/Monetta - 016 - 1264": 5, "Rolling Green - 304 - 687": 5, "Beulah Church - 006 - 921": 5, "Laurens 4 - 004 - 2095": 5, "Batesburg - 001 - 916": 5, "Roebuck Bethlehem - 119 - 2153": 5, "N. Augusta No. 27 - 027 - 112": 5, "Prosperity City - 036 - 1609": 5, "Lydia Mill - 015 - 2083": 5, "Cross Anchor Fire Station - 028 - 2133": 5, "Emerald High - 029 - 1906": 5, "Excelsior - 008 - 1335": 5, "Lyman Town Hall - 051 - 2140": 5, "Anderson Mill Baptist - 140 - 2143": 5, "Newberry Ward 1 - 001 - 1484": 5, "North Side - 010 - 569": 5, "Pleasant Cross - 013 - 1256": 5, "Friarsgate 2 - 432 - 1184": 5, "Woodruff Lakes - 344 - 670": 5, "Cross Hill - 026 - 2080": 5, "Beth - Eden - 010 - 1491": 5, "N. Augusta No. 29 - 029 - 107": 5, "Pelzer - 051 - 2220": 5, "Mountville - 016 - 2084": 5, "Silverstreet - 039 - 1477": 5, "Coldstream - 057 - 971": 5, "Piedmont - 295 - 2227": 5, "Verdery - 025 - 1935": 5, "Harbison 1 - 439 - 1187": 5, "Midway - 072 - 985": 5, "St. Phillips-Jolly Street - 042 - 1497": 5, "Sparrows Grace - 044 - 1898": 5, "Mt. Carmel - 001 - 1010": 5, "Gray Court - 020 - 2088": 5, "Hartford - 017 - 1478": 5, "Platt Springs 2 - 095 - 1003": 5, "Merriweather No.2 - 012 - 580": 5, "Joanna - 014 - 2082": 5, "Mccormick No. 2 - 009 - 1019": 5, "Platt Springs 1 - 094 - 1002": 5, "Shoals Junction - 032 - 1893": 5, "Reidville Fire Station - 118 - 2183": 5, "Pebble Stone Way - 008 - 1912": 5, "Fruit Hill - 005 - 1257": 5, "Rutherford Shoals - 040 - 1895": 5, "Bush River - 011 - 1476": 5, "Callison - 021 - 1920": 5, "Helena - 018 - 1483": 5, "Abner Creek Baptist - 030 - 2189": 5, "Boiling Springs South - 069 - 982": 5, "Laurens 2 - 002 - 2085": 5, "Ware Shoals - 014 - 1894": 5, "Johnstone - 020 - 1487": 5, "Hollow Creek - 015 - 930": 5, "Asheton Lakes - 232 - 676": 5, "Riverwalk - 300 - 662": 5, "Stonehaven - 322 - 667": 5, "Greenpond - 021 - 2092": 5, "Startex Fire Station - 090 - 2148": 5, "Laurens 1 - 001 - 2094": 5, "Red Bank - 018 - 933": 5, "Simpsonville 5 - 314 - 642": 5, "Verdmont - 368 - 638": 5, "Belvedere No. 62 - 062 - 114": 5, "Rocky Creek - 303 - 680": 5, "Civic Center - 030 - 1905": 5, "Sandridge - 020 - 1932": 5, "Trinity Ridge - 008 - 2105": 5, "Holstons - 009 - 1265": 5, "Duncan United Methodist - 032 - 2139": 5, "Savannah - 003 - 1017": 5, "Edgefield No.1 - 001 - 574": 5, "Standing Springs - 364 - 757": 5, "New Castle - 039 - 1900": 5, "Ascauga Lake No. 63 - 063 - 171": 5, "Mountain View - 286 - 747": 6, "Hendrix Elementary - 014 - 2193": 6, "Woodland Heights Recreation Center - 082 - 2150": 6, "Chester Ward 2 - 030 - 436": 6, "Rock Hill No. 6 - 035 - 1438": 6, "Great Falls - 035 - 453": 6, "India Hook - 043 - 1435": 6, "Fairgrounds - 075 - 1452": 6, "Carlisle Wesleyan - 126 - 2121": 6, "Mt. Zion Gospel Baptist - 106 - 2151": 6, "Harvest - 071 - 1442": 6, "Wilkinsville And Metcalf - 032 - 417": 6, "Pleasant Meadows - 028 - 426": 6, "River's Edge - 093 - 1399": 6, "Cleveland Elementary - 086 - 2161": 6, "Monarch Box 1 - 013 - 1337": 6, "Hazelwood - 013 - 448": 6, "Littlejohn's And Sarratt's - 022 - 418": 6, "Northwestern - 049 - 1441": 6, "Eureka Mill - 010 - 439": 6, "Ben Avon Methodist - 128 - 2176": 6, "Cedar Grove Baptist - 033 - 2235": 6, "Baton Rouge - 002 - 435": 6, "Grassy Pond - 018 - 410": 6, "Blackstock - 001 - 581": 6, "Gold Hill - 036 - 1594": 6, "Laurel Creek - 063 - 1449": 6, "Trinity Methodist - 073 - 2181": 6, "Pauline Glenn Springs Elementary - 060 - 2135": 6, "Wilksburg - 024 - 440": 6, "Santuck - 016 - 1344": 6, "Ebenezer - 013 - 1444": 6, "Harrisburg - 037 - 1596": 6, "Ashworth - 004 - 407": 6, "Mayo Elementary - 053 - 2196": 6, "Travelers Rest 2 - 366 - 750": 6, "Gaffney Ward No. 1 - 012 - 429": 6, "Mcconnells - 022 - 1390": 6, "Powell Saxon Una - 131 - 2187": 6, "Ninety Nine And Cherokee Falls - 026 - 416": 6, "West View Elementary - 098 - 2190": 6, "Old Pointe - 072 - 1443": 6, "Oakwood - 029 - 1454": 6, "Hickory Grove - 018 - 1387": 6, "Cornerstone Baptist - 078 - 2165": 6, "Kelton - 011 - 1346": 6, "Erwin Farm - 009 - 1599": 6, "Lockhart - 012 - 1347": 6, "The Lodge - 040 - 1592": 6, "Bowling Green - 005 - 1383": 6, "Larne - 091 - 1462": 6, "Fox Chase - 349 - 741": 6, "Fort Mill No. 2 - 058 - 1414": 6, "Wylie - 089 - 1397": 6, "Springdale - 086 - 1437": 6, "Kanawha - 095 - 1472": 6, "Bethany Baptist - 101 - 2160": 6, "Ogden - 028 - 1403": 6, "Cannon Mill - 007 - 1394": 6, "Baxter - 094 - 1473": 6, "Jonesville Box 2 - 010 - 1348": 6, "Frohawk - 350 - 751": 6, "Cowpens Depot Museum - 114 - 2125": 6, "Mt. Calvary Presbyterian - 096 - 2136": 6, "Rosewood - 048 - 1436": 6, "Mt. Gallant - 025 - 1434": 6, "Lando/Lansford - 034 - 454": 6, "Palmetto - 068 - 1431": 6, "Union Ward 1 Box 1 - 017 - 1331": 6, "Ebinport - 051 - 1453": 6, "Fairforest Middle School - 035 - 2145": 6, "Fort Mill No. 6 - 054 - 1426": 6, "Chester Ward 3 - 031 - 451": 6, "Tubbs Mountain - 334 - 745": 6, "Union Ward 4 Box 1 - 021 - 1349": 6, "Fort Mill No. 4 - 046 - 1423": 6, "Spartanburg High School - 076 - 2179": 6, "Pleasant Grove - 027 - 411": 6, "Morningside Baptist - 007 - 2177": 6, "Hope - 141 - 2147": 6, "River Road - 039 - 1593": 6, "Tigerville - 330 - 749": 6, "Ebenezer Baptist - 088 - 2158": 6, "Trade - 332 - 2247": 6, "Osceola - 038 - 1595": 6, "Rock Hill No. 2 - 031 - 1439": 6, "Anderson Road - 056 - 1607": 6, "Black Horse Run - 035 - 1598": 6, "Blackstock - 004 - 449": 6, "Chapman High School - 045 - 2197": 6, "Woodard - 021 - 598": 6, "Cowpens Fire Station - 026 - 2124": 6, "Lake House - 002 - 1591": 6, "Cudd Memorial - 109 - 2173": 6, "D. R. Hill Middle School - 138 - 2114": 6, "Hopewell - 079 - 1413": 6, "Ferry Branch - 076 - 1405": 6, "Tools Fork - 073 - 1401": 6, "Travelers Rest 1 - 365 - 743": 6, "Shoreline - 050 - 1430": 6, "Mill Creek - 081 - 1395": 6, "Oakland Elementary - 111 - 2118": 6, "Celanese - 096 - 1605": 6, "Rodman - 022 - 442": 6, "Fort Mill No. 3 - 017 - 1417": 6, "Jesse Boyd Elementary - 120 - 2168": 6, "Halsellville - 012 - 450": 6, "Rock Hill No. 3 - 032 - 1440": 6, "Mt. Moriah Baptist - 068 - 2172": 6, "Cotton Belt - 011 - 1385": 6, "New Home - 057 - 1466": 6, "Rebirth Missionary Baptist - 004 - 2236": 6, "Park Hills Elementary - 132 - 2185": 6, "Chesnee Elementary - 130 - 2186": 6, "Mt. Holly - 023 - 1461": 6, "Carolina - 074 - 1421": 6, "Cannons Elementary - 016 - 2127": 6, "Greater St. James - 116 - 2113": 6, "Rock Creek - 092 - 1469": 6, "Chester Ward 5 - 033 - 452": 6, "Alma Mill - 002 - 425": 6, "Newport - 024 - 1446": 6, "Macedonia - 023 - 409": 6, "Gold Hill - 066 - 1427": 6, "Boiling Springs Elementary - 123 - 2129": 6, "Bullocks Creek - 006 - 1388": 6, "Gowensville - 264 - 2251": 6, "Daniel Morgan Technology Center - 122 - 2166": 6, "Waterstone - 067 - 1433": 6, "Gaffney Ward No. 4 - 015 - 430": 6, "Eastside Baptist - 105 - 2169": 6, "Filbert - 014 - 1386": 6, "Gaffney Ward No. 2 - 013 - 428": 6, "Putman - 015 - 1339": 6, "Hayne Baptist - 041 - 2144": 6, "Gaffney Ward No. 6 - 017 - 431": 6, "Adnah - 070 - 1465": 6, "Goucher And Thicketty - 019 - 420": 6, "Dayton Fire Station - 031 - 2171": 6, "Rock Hill No. 8 - 037 - 1411": 6, "Carlisle Fosters Grove - 113 - 2120": 6, "Orchard Park - 061 - 1471": 6, "Allens - 001 - 422": 6, "Ezells And Butler - 011 - 406": 6, "Chester Ward 4 - 032 - 438": 6, "Manchester - 080 - 1606": 6, "Roosevelt - 090 - 1467": 6, "Pacolet Elementary - 129 - 2175": 6, "Fewell Park - 045 - 1456": 6, "Jonesville Box 1 - 009 - 1352": 6, "Catawba - 008 - 1404": 6, "Boiling Springs 9Th Grade - 008 - 2191": 6, "Castle Rock - 348 - 2249": 6, "Allison Creek - 055 - 1445": 6, "York No. 1 - 041 - 1392": 6, "Victor Mill Methodist - 095 - 2234": 6, "Boling Springs Jr. High - 124 - 2119": 6, "Tega Cay - 069 - 1429": 6, "Adamsburg - 001 - 1345": 6, "Southside Baptist - 075 - 2159": 6, "Six Mile - 085 - 1406": 6, "Shelley Mullis - 034 - 1590": 6, "Glendale Fire Station - 038 - 2122": 6, "White Stone Methodist - 108 - 2123": 6, "Lake Bowen Baptist - 011 - 2192": 6, "Lakeshore - 020 - 1474": 6, "Lyman Elementary - 139 - 2237": 6, "Gramling Methodist - 040 - 2198": 6, "Fort Lawn - 011 - 445": 6, "Independence - 021 - 1409": 6, "Clover - 009 - 1468": 6, "Van Wyck - 036 - 1600": 6, "Gladden Grove - 006 - 586": 6, "Oneal - 360 - 746": 6, "Blacksburg Ward No. 1 - 005 - 414": 6, "Baldwin Mill - 001 - 434": 6, "Union Ward 2 - 019 - 1333": 6, "Darby Ridge - 247 - 742": 6, "Nation Ford - 082 - 1419": 6, "University - 052 - 1457": 6, "Sharon - 038 - 1389": 6, "Pleasant Valley - 021 - 1597": 6, "White Plains - 031 - 419": 6, "Chapman Elementary - 125 - 2174": 6, "Tyger River - 367 - 2248": 6, "Rossville - 023 - 447": 6, "Gaffney Ward No. 5 - 016 - 432": 6, "Bethel School - 004 - 1470": 6, "Beaumont Methodist - 084 - 2170": 6, "Jesse Bobo Elementary - 107 - 2162": 6, "Draytonville - 010 - 423": 6, "Fort Mill No. 1 - 015 - 1416": 6, "Sandy Flat - 307 - 744": 6, "Steele Creek - 064 - 1425": 6, "Bethany - 001 - 1382": 6, "Bonham - 003 - 1336": 6, "Pole Branch - 084 - 1464": 6, "Lakewood - 062 - 1448": 6, "Antioch And Kings Creek - 003 - 413": 6, "Landrum United Methodist - 050 - 2241": 6, "Pleasant Road - 065 - 1432": 6, "Woods - 033 - 408": 6, "Hollis Lakes - 078 - 1450": 6, "Converse Fire Station - 024 - 2167": 6, "Airport - 030 - 1447": 6, "Landrum High School - 013 - 2240": 6, "Boiling Springs High School - 127 - 2116": 6, "New Hope - 013 - 590": 6, "Timber Ridge - 030 - 421": 6, "Blacksburg Ward No. 2 - 006 - 415": 6, "Gaffney Ward No. 3 - 014 - 433": 6, "Union Ward 1 Box 2 - 018 - 1332": 6, "Cherokee Springs Fire Station - 019 - 2117": 6, "York No. 2 - 042 - 1393": 6, "Delphia - 012 - 1391": 6, "Morgan - 024 - 405": 6, "Whitlock Jr. High - 100 - 2126": 6, "Richburg - 021 - 444": 6, "Fort Mill No. 5 - 053 - 1422": 6, "Motlow Creek Baptist - 054 - 2239": 6, "St. John's Lutheran - 072 - 2178": 6, "Highland Park - 019 - 1460": 6, "Possum Hollow - 032 - 1569": 6, "River Hills - 003 - 1398": 6, "Arcadia Elementary - 003 - 2163": 6, "Dobys Bridge - 059 - 1415": 6, "Holly Grove-Buffalo - 020 - 412": 6, "Boiling Springs Intermediate - 112 - 2128": 6, "Swofford Career Center - 057 - 2112": 6, "Musgrove Mill - 025 - 424": 6, "Windjammer - 016 - 1428": 6, "Edgewood - 044 - 1410": 6, "Rock Hill No. 5 - 034 - 1458": 6, "Oakridge - 027 - 1402": 6, "Rock Hill No. 7 - 036 - 1455": 6, "Riverview - 060 - 1424": 6, "Skyland - 316 - 2250": 6, "Lowrys - 018 - 441": 6, "West Springs - 023 - 1340": 6, "Edgemoor - 009 - 443": 6, "Clifdale Elementary - 022 - 2180": 6, "E.P. Todd Elementary - 018 - 2152": 6, "Croft Baptist - 099 - 2155": 6, "Cooley Springs Baptist - 012 - 2195": 6, "C.C. Woodson Recreation - 070 - 2164": 6, "Lesslie - 047 - 1407": 6, "Springfield - 087 - 1418": 6, "Fairforest Elementary - 029 - 2115": 6, "Limestone Mill - 021 - 427": 6, "Northside - 026 - 1459": 6, "Maridell - 275 - 748": 6, "Beckhamville - 003 - 446": 6, "Tirzah - 040 - 1400": 6, "Hampton Mill - 010 - 1463": 6, "Neelys Creek - 083 - 1408": 6, "White Oak - 020 - 597": 6, "Bethel - 002 - 1396": 6, "Chester Ward 1 - 029 - 437": 6, "Smyrna - 039 - 1384": 6, "Friendship - 077 - 1412": 6, "Stateline - 088 - 1420": 6, "Monarch Box 2 - 014 - 1353": 6, "Rock Hill No. 4 - 033 - 1451": 6, "Holly Springs Baptist - 044 - 2238": 6}